{
  "ControlStates": {
    "scr_XMLNabavniNalog": {
      "AllowAccessToGlobals": true,
      "ControlPropertyState": [
        {
          "AFDDataSourceName": "",
          "AutoRuleBindingEnabled": false,
          "AutoRuleBindingString": "RGBA(234, 234, 234, 1)",
          "InvariantPropertyName": "Fill",
          "IsLockable": false,
          "NameMapSourceSchema": "?"
        },
        "ImagePosition",
        "Height",
        "Width",
        "Size",
        "Orientation",
        "LoadingSpinner",
        "LoadingSpinnerColor",
        {
          "AFDDataSourceName": "",
          "AutoRuleBindingEnabled": false,
          "AutoRuleBindingString": "If(!IsBlank(SelectedFile),\nIfError(GetXML_Nabavni_Nalog.Run(SelectedFile, SelectedFolder),\n    Notify(\"Error occurred while Get request, check if file exists.\",NotificationType.Error,5000),\n    UpdateContext({purchase: GetXML_Nabavni_Nalog.Run(SelectedFile, SelectedFolder)})\n);\n\nUpdateContext({purchase_line: purchase.purchase_line});\nUpdateContext({purchase_header: ParseJSON(purchase.purchase_header)});\n\nClear(colPurchaseLines);\nForAll(\n    ParseJSON(purchase_line),\n    Collect(\n        colPurchaseLines,\n        {\n             Document_Type: Text(ThisRecord.Document_Type),\n              'Buy-from_Vendor_No.': Text(ThisRecord.'Buy-from_Vendor_No.'),\n              Document_No: Text(ThisRecord.Document_No),\n              Line_No: Text(ThisRecord.Line_No),\n              Type: Text(ThisRecord.Type),\n              Item_No: Text(ThisRecord.Item_No),\n              Location_Code: Text(ThisRecord.Location_Code),\n              Posting_Group: Text(ThisRecord.Posting_Group),\n              Description: Text(ThisRecord.Description),\n              Unit_Of_Measure: Text(ThisRecord.Unit_Of_Measure),\n              Quantity: Text(ThisRecord.Quantity),\n              LOT_No: Text(ThisRecord.LOT_No),\n              Exp_Date: Text(ThisRecord.Exp_Date)\n        }\n    );\n);\n\nClearCollect(colOriginalPurchaseLines, colPurchaseLines);\n)",
          "InvariantPropertyName": "OnVisible",
          "IsLockable": false,
          "NameMapSourceSchema": "?"
        }
      ],
      "IsAutoGenerated": false,
      "IsComponentDefinition": false,
      "IsDataControl": false,
      "IsFromScreenLayout": false,
      "IsGroupControl": false,
      "IsLocked": false,
      "LayoutName": "",
      "MetaDataIDKey": "",
      "Name": "scr_XMLNabavniNalog",
      "OptimizeForDevices": "Off",
      "ParentIndex": 0,
      "PersistMetaDataIDKey": false,
      "Properties": [
        {
          "Category": "Design",
          "PropertyName": "LoadingSpinnerColor",
          "RuleProviderType": "Unknown"
        },
        {
          "Category": "Design",
          "PropertyName": "Width",
          "RuleProviderType": "Unknown"
        },
        {
          "Category": "Design",
          "PropertyName": "Height",
          "RuleProviderType": "Unknown"
        },
        {
          "Category": "Design",
          "PropertyName": "ImagePosition",
          "RuleProviderType": "Unknown"
        },
        {
          "Category": "Design",
          "PropertyName": "LoadingSpinner",
          "RuleProviderType": "Unknown"
        },
        {
          "Category": "Design",
          "PropertyName": "Fill",
          "RuleProviderType": "Unknown"
        },
        {
          "Category": "Design",
          "PropertyName": "Orientation",
          "RuleProviderType": "Unknown"
        },
        {
          "Category": "Design",
          "PropertyName": "Size",
          "RuleProviderType": "Unknown"
        },
        {
          "Category": "Behavior",
          "PropertyName": "OnVisible",
          "RuleProviderType": "User"
        }
      ],
      "StyleName": "defaultScreenStyle",
      "Type": "ControlInfo"
    }
  },
  "TopParentName": "scr_XMLNabavniNalog"
}