{
  "ComponentAllowCustomization": true,
  "ComponentChangedSinceFileImport": true,
  "ComponentDefinitionInfo": {
    "AllowAccessToGlobals": false,
    "Children": [
      {
        "AllowAccessToGlobals": true,
        "Children": [
          {
            "AllowAccessToGlobals": true,
            "Children": [],
            "ControlPropertyState": [
              "Icon",
              "Color",
              "DisabledColor",
              "PressedColor",
              "HoverColor",
              "Fill",
              "DisabledFill",
              "PressedFill",
              "HoverFill",
              "DisplayMode",
              "X",
              "Y",
              {
                "AFDDataSourceName": "",
                "AutoRuleBindingEnabled": false,
                "AutoRuleBindingString": "",
                "InvariantPropertyName": "Width",
                "IsLockable": false,
                "NameMapSourceSchema": "?"
              },
              {
                "AFDDataSourceName": "",
                "AutoRuleBindingEnabled": false,
                "AutoRuleBindingString": "",
                "InvariantPropertyName": "Height",
                "IsLockable": false,
                "NameMapSourceSchema": "?"
              },
              "BorderStyle",
              "BorderColor",
              "DisabledBorderColor",
              "PressedBorderColor",
              "HoverBorderColor",
              "FocusedBorderColor",
              "ZIndex",
              "BorderThickness",
              "FocusedBorderThickness"
            ],
            "ControlUniqueId": "514",
            "DynamicProperties": [
              {
                "ControlPropertyState": "FillPortions",
                "PropertyName": "FillPortions",
                "Rule": {
                  "Category": "Design",
                  "InvariantScript": "0",
                  "Property": "FillPortions",
                  "RuleProviderType": "Unknown"
                }
              },
              {
                "ControlPropertyState": {
                  "AFDDataSourceName": "",
                  "AutoRuleBindingEnabled": false,
                  "AutoRuleBindingString": "",
                  "InvariantPropertyName": "AlignInContainer",
                  "IsLockable": false,
                  "NameMapSourceSchema": "?"
                },
                "PropertyName": "AlignInContainer",
                "Rule": {
                  "Category": "Design",
                  "InvariantScript": "AlignInContainer.Center",
                  "Property": "AlignInContainer",
                  "RuleProviderType": "Unknown"
                }
              },
              {
                "ControlPropertyState": "LayoutMinWidth",
                "PropertyName": "LayoutMinWidth",
                "Rule": {
                  "Category": "Design",
                  "InvariantScript": "64",
                  "Property": "LayoutMinWidth",
                  "RuleProviderType": "Unknown"
                }
              },
              {
                "ControlPropertyState": "LayoutMinHeight",
                "PropertyName": "LayoutMinHeight",
                "Rule": {
                  "Category": "Design",
                  "InvariantScript": "64",
                  "Property": "LayoutMinHeight",
                  "RuleProviderType": "Unknown"
                }
              }
            ],
            "HasDynamicProperties": true,
            "Index": 0,
            "IsAutoGenerated": false,
            "IsDataControl": false,
            "IsFromScreenLayout": false,
            "IsGroupControl": false,
            "IsLocked": false,
            "LayoutName": "",
            "MetaDataIDKey": "",
            "Name": "Icon2",
            "OptimizeForDevices": "Off",
            "Parent": "Container10",
            "PersistMetaDataIDKey": false,
            "PublishOrderIndex": 0,
            "Rules": [
              {
                "Category": "Design",
                "InvariantScript": "Icon.BackArrow",
                "Property": "Icon",
                "RuleProviderType": "Unknown"
              },
              {
                "Category": "Design",
                "InvariantScript": "RGBA(89, 0, 0, 1)",
                "Property": "Color",
                "RuleProviderType": "Unknown"
              },
              {
                "Category": "Design",
                "InvariantScript": "RGBA(244, 244, 244, 1)",
                "Property": "DisabledColor",
                "RuleProviderType": "Unknown"
              },
              {
                "Category": "Design",
                "InvariantScript": "ColorFade(Self.Color, -20%)",
                "Property": "PressedColor",
                "RuleProviderType": "Unknown"
              },
              {
                "Category": "Design",
                "InvariantScript": "ColorFade(Self.Color, 20%)",
                "Property": "HoverColor",
                "RuleProviderType": "Unknown"
              },
              {
                "Category": "Design",
                "InvariantScript": "RGBA(0, 0, 0, 0)",
                "Property": "Fill",
                "RuleProviderType": "Unknown"
              },
              {
                "Category": "Design",
                "InvariantScript": "Self.Fill",
                "Property": "DisabledFill",
                "RuleProviderType": "Unknown"
              },
              {
                "Category": "Design",
                "InvariantScript": "Self.Fill",
                "Property": "PressedFill",
                "RuleProviderType": "Unknown"
              },
              {
                "Category": "Design",
                "InvariantScript": "Self.Fill",
                "Property": "HoverFill",
                "RuleProviderType": "Unknown"
              },
              {
                "Category": "Design",
                "InvariantScript": "DisplayMode.Edit",
                "Property": "DisplayMode",
                "RuleProviderType": "Unknown"
              },
              {
                "Category": "Design",
                "InvariantScript": "0",
                "Property": "X",
                "RuleProviderType": "Unknown"
              },
              {
                "Category": "Design",
                "InvariantScript": "0",
                "Property": "Y",
                "RuleProviderType": "Unknown"
              },
              {
                "Category": "Design",
                "InvariantScript": "100",
                "Property": "Width",
                "RuleProviderType": "Unknown"
              },
              {
                "Category": "Design",
                "InvariantScript": "36",
                "Property": "Height",
                "RuleProviderType": "Unknown"
              },
              {
                "Category": "Design",
                "InvariantScript": "BorderStyle.Solid",
                "Property": "BorderStyle",
                "RuleProviderType": "Unknown"
              },
              {
                "Category": "Design",
                "InvariantScript": "RGBA(89, 0, 0, 1)",
                "Property": "BorderColor",
                "RuleProviderType": "Unknown"
              },
              {
                "Category": "Design",
                "InvariantScript": "RGBA(166, 166, 166, 1)",
                "Property": "DisabledBorderColor",
                "RuleProviderType": "Unknown"
              },
              {
                "Category": "Design",
                "InvariantScript": "ColorFade(Self.BorderColor, -20%)",
                "Property": "PressedBorderColor",
                "RuleProviderType": "Unknown"
              },
              {
                "Category": "Design",
                "InvariantScript": "ColorFade(Self.BorderColor, 20%)",
                "Property": "HoverBorderColor",
                "RuleProviderType": "Unknown"
              },
              {
                "Category": "Design",
                "InvariantScript": "Self.BorderColor",
                "Property": "FocusedBorderColor",
                "RuleProviderType": "Unknown"
              },
              {
                "Category": "Design",
                "InvariantScript": "1",
                "Property": "ZIndex",
                "RuleProviderType": "Unknown"
              },
              {
                "Category": "Design",
                "InvariantScript": "0",
                "Property": "BorderThickness",
                "RuleProviderType": "Unknown"
              },
              {
                "Category": "Design",
                "InvariantScript": "2",
                "Property": "FocusedBorderThickness",
                "RuleProviderType": "Unknown"
              }
            ],
            "StyleName": "defaultIconStyle",
            "Template": {
              "CustomGroupControlTemplateName": "",
              "FirstParty": true,
              "Id": "http://microsoft.com/appmagic/icon",
              "IsComponentDefinition": false,
              "IsCustomGroupControlTemplate": false,
              "IsPremiumPcfControl": false,
              "LastModifiedTimestamp": "0",
              "Name": "icon",
              "OverridableProperties": {},
              "Version": "2.5.0"
            },
            "Type": "ControlInfo",
            "VariantName": "BackArrow"
          },
          {
            "AllowAccessToGlobals": true,
            "Children": [],
            "ControlPropertyState": [
              "Height",
              "X",
              "Y",
              "Width",
              "DisplayMode",
              "ZIndex",
              {
                "AFDDataSourceName": "",
                "AutoRuleBindingEnabled": false,
                "AutoRuleBindingString": "\"Text\"",
                "InvariantPropertyName": "Text",
                "IsLockable": false,
                "NameMapSourceSchema": "?"
              }
            ],
            "ControlUniqueId": "515",
            "DynamicProperties": [
              {
                "ControlPropertyState": "FillPortions",
                "PropertyName": "FillPortions",
                "Rule": {
                  "Category": "Design",
                  "InvariantScript": "0",
                  "Property": "FillPortions",
                  "RuleProviderType": "Unknown"
                }
              },
              {
                "ControlPropertyState": {
                  "AFDDataSourceName": "",
                  "AutoRuleBindingEnabled": false,
                  "AutoRuleBindingString": "",
                  "InvariantPropertyName": "AlignInContainer",
                  "IsLockable": false,
                  "NameMapSourceSchema": "?"
                },
                "PropertyName": "AlignInContainer",
                "Rule": {
                  "Category": "Design",
                  "InvariantScript": "AlignInContainer.Center",
                  "Property": "AlignInContainer",
                  "RuleProviderType": "Unknown"
                }
              },
              {
                "ControlPropertyState": "LayoutMinWidth",
                "PropertyName": "LayoutMinWidth",
                "Rule": {
                  "Category": "Design",
                  "InvariantScript": "96",
                  "Property": "LayoutMinWidth",
                  "RuleProviderType": "Unknown"
                }
              },
              {
                "ControlPropertyState": "LayoutMinHeight",
                "PropertyName": "LayoutMinHeight",
                "Rule": {
                  "Category": "Design",
                  "InvariantScript": "32",
                  "Property": "LayoutMinHeight",
                  "RuleProviderType": "Unknown"
                }
              }
            ],
            "HasDynamicProperties": true,
            "Index": 0,
            "IsAutoGenerated": false,
            "IsDataControl": false,
            "IsFromScreenLayout": false,
            "IsGroupControl": false,
            "IsLocked": false,
            "LayoutName": "",
            "MetaDataIDKey": "",
            "Name": "TextCanvas3",
            "OptimizeForDevices": "Off",
            "Parent": "Container10",
            "PersistMetaDataIDKey": false,
            "PublishOrderIndex": 0,
            "Rules": [
              {
                "Category": "Data",
                "InvariantScript": "\"Naslov\"",
                "Property": "Text",
                "RuleProviderType": "User"
              },
              {
                "Category": "Design",
                "InvariantScript": "32",
                "Property": "Height",
                "RuleProviderType": "Unknown"
              },
              {
                "Category": "Design",
                "InvariantScript": "0",
                "Property": "X",
                "RuleProviderType": "Unknown"
              },
              {
                "Category": "Design",
                "InvariantScript": "0",
                "Property": "Y",
                "RuleProviderType": "Unknown"
              },
              {
                "Category": "Design",
                "InvariantScript": "96",
                "Property": "Width",
                "RuleProviderType": "Unknown"
              },
              {
                "Category": "Design",
                "InvariantScript": "DisplayMode.Edit",
                "Property": "DisplayMode",
                "RuleProviderType": "Unknown"
              },
              {
                "Category": "Design",
                "InvariantScript": "2",
                "Property": "ZIndex",
                "RuleProviderType": "Unknown"
              }
            ],
            "StyleName": "",
            "Template": {
              "CustomGroupControlTemplateName": "",
              "DynamicControlDefinitionJson": "{\"ControlNamespace\":\"PowerApps.CoreControls\",\"ControlConstructor\":\"TextCanvas\",\"DisplayNameKey\":\"TextCanvas\",\"Resources\":\"[{\\\"Type\\\":0,\\\"Path\\\":\\\"/PCF/prop-types.js\\\",\\\"ModifiedPath\\\":\\\"\\\",\\\"LoadingOrder\\\":1,\\\"IsControlSpecific\\\":false},{\\\"Type\\\":0,\\\"Path\\\":\\\"/PCF/react-fela.js\\\",\\\"ModifiedPath\\\":\\\"\\\",\\\"LoadingOrder\\\":2,\\\"IsControlSpecific\\\":false},{\\\"Type\\\":0,\\\"Path\\\":\\\"/PCF/fela.js\\\",\\\"ModifiedPath\\\":\\\"\\\",\\\"LoadingOrder\\\":3,\\\"IsControlSpecific\\\":false},{\\\"Type\\\":0,\\\"Path\\\":\\\"/PCF/fela-dom.js\\\",\\\"ModifiedPath\\\":\\\"\\\",\\\"LoadingOrder\\\":4,\\\"IsControlSpecific\\\":false},{\\\"Type\\\":0,\\\"Path\\\":\\\"/ctrllib/common/js/container.js\\\",\\\"ModifiedPath\\\":\\\"\\\",\\\"LoadingOrder\\\":5,\\\"IsControlSpecific\\\":false},{\\\"Type\\\":0,\\\"Path\\\":\\\"/ctrllib/PCFControls/js/PCFControlWrapper.js\\\",\\\"ModifiedPath\\\":\\\"\\\",\\\"LoadingOrder\\\":6,\\\"IsControlSpecific\\\":false},{\\\"Type\\\":0,\\\"Path\\\":\\\"/ctrllib/PcfControlProxy/js/PcfControlProxy.js\\\",\\\"ModifiedPath\\\":\\\"\\\",\\\"LoadingOrder\\\":7,\\\"IsControlSpecific\\\":false},{\\\"Type\\\":3,\\\"Path\\\":\\\"{\\\\\\\"Id\\\\\\\":\\\\\\\"ManifestTemplate\\\\\\\",\\\\\\\"Data\\\\\\\":{\\\\\\\"ConstructorName\\\\\\\":\\\\\\\"PowerApps.CoreControls.TextCanvas\\\\\\\",\\\\\\\"CustomControlId\\\\\\\":\\\\\\\"PowerApps.CoreControls.TextCanvas\\\\\\\",\\\\\\\"IsVirtual\\\\\\\":true,\\\\\\\"Properties\\\\\\\":{\\\\\\\"Resources\\\\\\\":[{\\\\\\\"Name\\\\\\\":\\\\\\\"/PCF/prop-types.js\\\\\\\",\\\\\\\"LoadOrder\\\\\\\":1,\\\\\\\"Type\\\\\\\":0,\\\\\\\"LibraryName\\\\\\\":null},{\\\\\\\"Name\\\\\\\":\\\\\\\"/PCF/react-fela.js\\\\\\\",\\\\\\\"LoadOrder\\\\\\\":2,\\\\\\\"Type\\\\\\\":0,\\\\\\\"LibraryName\\\\\\\":null},{\\\\\\\"Name\\\\\\\":\\\\\\\"/PCF/fela.js\\\\\\\",\\\\\\\"LoadOrder\\\\\\\":3,\\\\\\\"Type\\\\\\\":0,\\\\\\\"LibraryName\\\\\\\":null},{\\\\\\\"Name\\\\\\\":\\\\\\\"/PCF/fela-dom.js\\\\\\\",\\\\\\\"LoadOrder\\\\\\\":4,\\\\\\\"Type\\\\\\\":0,\\\\\\\"LibraryName\\\\\\\":null},{\\\\\\\"Name\\\\\\\":\\\\\\\"/ctrllib/common/js/container.js\\\\\\\",\\\\\\\"LoadOrder\\\\\\\":5,\\\\\\\"Type\\\\\\\":0,\\\\\\\"LibraryName\\\\\\\":null},{\\\\\\\"Name\\\\\\\":\\\\\\\"/ctrllib/PCFControls/js/PCFControlWrapper.js\\\\\\\",\\\\\\\"LoadOrder\\\\\\\":6,\\\\\\\"Type\\\\\\\":0,\\\\\\\"LibraryName\\\\\\\":null},{\\\\\\\"Name\\\\\\\":\\\\\\\"/ctrllib/PcfControlProxy/js/PcfControlProxy.js\\\\\\\",\\\\\\\"LoadOrder\\\\\\\":7,\\\\\\\"Type\\\\\\\":0,\\\\\\\"LibraryName\\\\\\\":null}],\\\\\\\"GroupDefinitions\\\\\\\":null,\\\\\\\"DataSetDefinitions\\\\\\\":{},\\\\\\\"Properties\\\\\\\":{\\\\\\\"Text\\\\\\\":{\\\\\\\"Required\\\\\\\":true,\\\\\\\"Usage\\\\\\\":0,\\\\\\\"DefaultValue\\\\\\\":\\\\\\\"Text\\\\\\\"},\\\\\\\"Size\\\\\\\":{\\\\\\\"Required\\\\\\\":true,\\\\\\\"Usage\\\\\\\":0,\\\\\\\"DefaultValue\\\\\\\":\\\\\\\"14\\\\\\\"},\\\\\\\"Weight\\\\\\\":{\\\\\\\"Required\\\\\\\":true,\\\\\\\"Usage\\\\\\\":0,\\\\\\\"DefaultValue\\\\\\\":\\\\\\\"Regular\\\\\\\"},\\\\\\\"Align\\\\\\\":{\\\\\\\"Required\\\\\\\":true,\\\\\\\"Usage\\\\\\\":0,\\\\\\\"DefaultValue\\\\\\\":\\\\\\\"Start\\\\\\\"},\\\\\\\"VerticalAlign\\\\\\\":{\\\\\\\"Required\\\\\\\":true,\\\\\\\"Usage\\\\\\\":0,\\\\\\\"DefaultValue\\\\\\\":\\\\\\\"Middle\\\\\\\"},\\\\\\\"AutoHeight\\\\\\\":{\\\\\\\"Required\\\\\\\":true,\\\\\\\"Usage\\\\\\\":0,\\\\\\\"DefaultValue\\\\\\\":\\\\\\\"false\\\\\\\"},\\\\\\\"Height\\\\\\\":{\\\\\\\"Required\\\\\\\":true,\\\\\\\"Usage\\\\\\\":0,\\\\\\\"DefaultValue\\\\\\\":\\\\\\\"32\\\\\\\"},\\\\\\\"Font\\\\\\\":{\\\\\\\"Required\\\\\\\":true,\\\\\\\"Usage\\\\\\\":1,\\\\\\\"DefaultValue\\\\\\\":\\\\\\\"\\\\\\\"},\\\\\\\"FontColor\\\\\\\":{\\\\\\\"Required\\\\\\\":true,\\\\\\\"Usage\\\\\\\":1,\\\\\\\"DefaultValue\\\\\\\":\\\\\\\"\\\\\\\"},\\\\\\\"FontItalic\\\\\\\":{\\\\\\\"Required\\\\\\\":true,\\\\\\\"Usage\\\\\\\":0,\\\\\\\"DefaultValue\\\\\\\":\\\\\\\"false\\\\\\\"},\\\\\\\"FontStrikethrough\\\\\\\":{\\\\\\\"Required\\\\\\\":true,\\\\\\\"Usage\\\\\\\":0,\\\\\\\"DefaultValue\\\\\\\":\\\\\\\"false\\\\\\\"},\\\\\\\"FontUnderline\\\\\\\":{\\\\\\\"Required\\\\\\\":true,\\\\\\\"Usage\\\\\\\":0,\\\\\\\"DefaultValue\\\\\\\":\\\\\\\"false\\\\\\\"},\\\\\\\"Wrap\\\\\\\":{\\\\\\\"Required\\\\\\\":true,\\\\\\\"Usage\\\\\\\":0,\\\\\\\"DefaultValue\\\\\\\":\\\\\\\"true\\\\\\\"},\\\\\\\"TabIndex\\\\\\\":{\\\\\\\"Required\\\\\\\":true,\\\\\\\"Usage\\\\\\\":1,\\\\\\\"DefaultValue\\\\\\\":\\\\\\\"\\\\\\\"},\\\\\\\"Tooltip\\\\\\\":{\\\\\\\"Required\\\\\\\":true,\\\\\\\"Usage\\\\\\\":1,\\\\\\\"DefaultValue\\\\\\\":\\\\\\\"\\\\\\\"}},\\\\\\\"FeatureUsage\\\\\\\":[{\\\\\\\"IsRequired\\\\\\\":true,\\\\\\\"Name\\\\\\\":\\\\\\\"ExplicitCommonEvents\\\\\\\"}]},\\\\\\\"Events\\\\\\\":null,\\\\\\\"CommonEvents\\\\\\\":null,\\\\\\\"DesignMap\\\\\\\":null,\\\\\\\"PropertyDependencies\\\\\\\":[],\\\\\\\"Children\\\\\\\":null}}\\\",\\\"ModifiedPath\\\":\\\"\\\",\\\"LoadingOrder\\\":8,\\\"IsControlSpecific\\\":false},{\\\"Type\\\":3,\\\"Path\\\":\\\"{\\\\\\\"Id\\\\\\\":\\\\\\\"ManifestPropertyTypes\\\\\\\",\\\\\\\"Data\\\\\\\":{\\\\\\\"Properties\\\\\\\":[{\\\\\\\"Name\\\\\\\":\\\\\\\"Text\\\\\\\",\\\\\\\"Type\\\\\\\":\\\\\\\"SingleLine_Text\\\\\\\",\\\\\\\"ComplexType\\\\\\\":\\\\\\\"None\\\\\\\",\\\\\\\"IsPrimary\\\\\\\":true,\\\\\\\"IsIncluded\\\\\\\":false},{\\\\\\\"Name\\\\\\\":\\\\\\\"Size\\\\\\\",\\\\\\\"Type\\\\\\\":\\\\\\\"Whole_None\\\\\\\",\\\\\\\"ComplexType\\\\\\\":\\\\\\\"None\\\\\\\",\\\\\\\"IsPrimary\\\\\\\":false,\\\\\\\"IsIncluded\\\\\\\":false},{\\\\\\\"Name\\\\\\\":\\\\\\\"Weight\\\\\\\",\\\\\\\"Type\\\\\\\":\\\\\\\"Enum\\\\\\\",\\\\\\\"ComplexType\\\\\\\":\\\\\\\"None\\\\\\\",\\\\\\\"IsPrimary\\\\\\\":false,\\\\\\\"IsIncluded\\\\\\\":false},{\\\\\\\"Name\\\\\\\":\\\\\\\"Align\\\\\\\",\\\\\\\"Type\\\\\\\":\\\\\\\"Enum\\\\\\\",\\\\\\\"ComplexType\\\\\\\":\\\\\\\"None\\\\\\\",\\\\\\\"IsPrimary\\\\\\\":false,\\\\\\\"IsIncluded\\\\\\\":false},{\\\\\\\"Name\\\\\\\":\\\\\\\"VerticalAlign\\\\\\\",\\\\\\\"Type\\\\\\\":\\\\\\\"Enum\\\\\\\",\\\\\\\"ComplexType\\\\\\\":\\\\\\\"None\\\\\\\",\\\\\\\"IsPrimary\\\\\\\":false,\\\\\\\"IsIncluded\\\\\\\":false},{\\\\\\\"Name\\\\\\\":\\\\\\\"AutoHeight\\\\\\\",\\\\\\\"Type\\\\\\\":\\\\\\\"TwoOptions\\\\\\\",\\\\\\\"ComplexType\\\\\\\":\\\\\\\"None\\\\\\\",\\\\\\\"IsPrimary\\\\\\\":false,\\\\\\\"IsIncluded\\\\\\\":false},{\\\\\\\"Name\\\\\\\":\\\\\\\"Height\\\\\\\",\\\\\\\"Type\\\\\\\":\\\\\\\"Whole_None\\\\\\\",\\\\\\\"ComplexType\\\\\\\":\\\\\\\"None\\\\\\\",\\\\\\\"IsPrimary\\\\\\\":false,\\\\\\\"IsIncluded\\\\\\\":false},{\\\\\\\"Name\\\\\\\":\\\\\\\"Font\\\\\\\",\\\\\\\"Type\\\\\\\":\\\\\\\"SingleLine_Text\\\\\\\",\\\\\\\"ComplexType\\\\\\\":\\\\\\\"Font\\\\\\\",\\\\\\\"IsPrimary\\\\\\\":false,\\\\\\\"IsIncluded\\\\\\\":false},{\\\\\\\"Name\\\\\\\":\\\\\\\"FontColor\\\\\\\",\\\\\\\"Type\\\\\\\":\\\\\\\"SingleLine_Text\\\\\\\",\\\\\\\"ComplexType\\\\\\\":\\\\\\\"FontColor\\\\\\\",\\\\\\\"IsPrimary\\\\\\\":false,\\\\\\\"IsIncluded\\\\\\\":false},{\\\\\\\"Name\\\\\\\":\\\\\\\"FontItalic\\\\\\\",\\\\\\\"Type\\\\\\\":\\\\\\\"TwoOptions\\\\\\\",\\\\\\\"ComplexType\\\\\\\":\\\\\\\"Italics\\\\\\\",\\\\\\\"IsPrimary\\\\\\\":false,\\\\\\\"IsIncluded\\\\\\\":false},{\\\\\\\"Name\\\\\\\":\\\\\\\"FontStrikethrough\\\\\\\",\\\\\\\"Type\\\\\\\":\\\\\\\"TwoOptions\\\\\\\",\\\\\\\"ComplexType\\\\\\\":\\\\\\\"Strikethrough\\\\\\\",\\\\\\\"IsPrimary\\\\\\\":false,\\\\\\\"IsIncluded\\\\\\\":false},{\\\\\\\"Name\\\\\\\":\\\\\\\"FontUnderline\\\\\\\",\\\\\\\"Type\\\\\\\":\\\\\\\"TwoOptions\\\\\\\",\\\\\\\"ComplexType\\\\\\\":\\\\\\\"Underline\\\\\\\",\\\\\\\"IsPrimary\\\\\\\":false,\\\\\\\"IsIncluded\\\\\\\":false},{\\\\\\\"Name\\\\\\\":\\\\\\\"Wrap\\\\\\\",\\\\\\\"Type\\\\\\\":\\\\\\\"TwoOptions\\\\\\\",\\\\\\\"ComplexType\\\\\\\":\\\\\\\"None\\\\\\\",\\\\\\\"IsPrimary\\\\\\\":false,\\\\\\\"IsIncluded\\\\\\\":false},{\\\\\\\"Name\\\\\\\":\\\\\\\"TabIndex\\\\\\\",\\\\\\\"Type\\\\\\\":\\\\\\\"Whole_None\\\\\\\",\\\\\\\"ComplexType\\\\\\\":\\\\\\\"\\\\\\\",\\\\\\\"IsPrimary\\\\\\\":false,\\\\\\\"IsIncluded\\\\\\\":false},{\\\\\\\"Name\\\\\\\":\\\\\\\"Tooltip\\\\\\\",\\\\\\\"Type\\\\\\\":\\\\\\\"SingleLine_Text\\\\\\\",\\\\\\\"ComplexType\\\\\\\":\\\\\\\"\\\\\\\",\\\\\\\"IsPrimary\\\\\\\":false,\\\\\\\"IsIncluded\\\\\\\":false},{\\\\\\\"Name\\\\\\\":\\\\\\\"PCFTeamsTheme\\\\\\\",\\\\\\\"Type\\\\\\\":\\\\\\\"String\\\\\\\",\\\\\\\"ComplexType\\\\\\\":\\\\\\\"\\\\\\\",\\\\\\\"IsPrimary\\\\\\\":false,\\\\\\\"IsIncluded\\\\\\\":true},{\\\\\\\"Name\\\\\\\":\\\\\\\"X\\\\\\\",\\\\\\\"Type\\\\\\\":\\\\\\\"Number\\\\\\\",\\\\\\\"ComplexType\\\\\\\":\\\\\\\"\\\\\\\",\\\\\\\"IsPrimary\\\\\\\":false,\\\\\\\"IsIncluded\\\\\\\":true},{\\\\\\\"Name\\\\\\\":\\\\\\\"Y\\\\\\\",\\\\\\\"Type\\\\\\\":\\\\\\\"Number\\\\\\\",\\\\\\\"ComplexType\\\\\\\":\\\\\\\"\\\\\\\",\\\\\\\"IsPrimary\\\\\\\":false,\\\\\\\"IsIncluded\\\\\\\":true},{\\\\\\\"Name\\\\\\\":\\\\\\\"Width\\\\\\\",\\\\\\\"Type\\\\\\\":\\\\\\\"Number\\\\\\\",\\\\\\\"ComplexType\\\\\\\":\\\\\\\"\\\\\\\",\\\\\\\"IsPrimary\\\\\\\":false,\\\\\\\"IsIncluded\\\\\\\":true},{\\\\\\\"Name\\\\\\\":\\\\\\\"Visible\\\\\\\",\\\\\\\"Type\\\\\\\":\\\\\\\"Boolean\\\\\\\",\\\\\\\"ComplexType\\\\\\\":\\\\\\\"\\\\\\\",\\\\\\\"IsPrimary\\\\\\\":false,\\\\\\\"IsIncluded\\\\\\\":true},{\\\\\\\"Name\\\\\\\":\\\\\\\"DisplayMode\\\\\\\",\\\\\\\"Type\\\\\\\":\\\\\\\"DisplayMode\\\\\\\",\\\\\\\"ComplexType\\\\\\\":\\\\\\\"\\\\\\\",\\\\\\\"IsPrimary\\\\\\\":false,\\\\\\\"IsIncluded\\\\\\\":true}]}}\\\",\\\"ModifiedPath\\\":\\\"\\\",\\\"LoadingOrder\\\":9,\\\"IsControlSpecific\\\":false},{\\\"Type\\\":3,\\\"Path\\\":\\\"{\\\\\\\"Id\\\\\\\":\\\\\\\"PowerAppsControlInfo\\\\\\\",\\\\\\\"Data\\\\\\\":{\\\\\\\"TemplateVersion\\\\\\\":1,\\\\\\\"Version\\\\\\\":\\\\\\\"0.0.25\\\\\\\",\\\\\\\"IsFirstParty\\\\\\\":true}}\\\",\\\"ModifiedPath\\\":\\\"\\\",\\\"LoadingOrder\\\":10,\\\"IsControlSpecific\\\":false},{\\\"Type\\\":0,\\\"Path\\\":\\\"/PCFControls/PowerApps_CoreControls_TextCanvas/TextCanvas.js\\\",\\\"ModifiedPath\\\":\\\"\\\",\\\"LoadingOrder\\\":11,\\\"IsControlSpecific\\\":true},{\\\"Type\\\":2,\\\"Path\\\":\\\"/PCFControls/PowerApps_CoreControls_TextCanvas/strings/TextCanvas.1033.resx\\\",\\\"ModifiedPath\\\":\\\"\\\",\\\"LoadingOrder\\\":10,\\\"IsControlSpecific\\\":true},{\\\"Type\\\":5,\\\"Path\\\":\\\"/PCFControls/PowerApps_CoreControls_TextCanvas/strings/TextCanvas.1025.json\\\",\\\"ModifiedPath\\\":\\\"\\\",\\\"LoadingOrder\\\":13,\\\"IsControlSpecific\\\":true},{\\\"Type\\\":5,\\\"Path\\\":\\\"/PCFControls/PowerApps_CoreControls_TextCanvas/strings/TextCanvas.1026.json\\\",\\\"ModifiedPath\\\":\\\"\\\",\\\"LoadingOrder\\\":13,\\\"IsControlSpecific\\\":true},{\\\"Type\\\":5,\\\"Path\\\":\\\"/PCFControls/PowerApps_CoreControls_TextCanvas/strings/TextCanvas.1027.json\\\",\\\"ModifiedPath\\\":\\\"\\\",\\\"LoadingOrder\\\":13,\\\"IsControlSpecific\\\":true},{\\\"Type\\\":5,\\\"Path\\\":\\\"/PCFControls/PowerApps_CoreControls_TextCanvas/strings/TextCanvas.1028.json\\\",\\\"ModifiedPath\\\":\\\"\\\",\\\"LoadingOrder\\\":13,\\\"IsControlSpecific\\\":true},{\\\"Type\\\":5,\\\"Path\\\":\\\"/PCFControls/PowerApps_CoreControls_TextCanvas/strings/TextCanvas.1029.json\\\",\\\"ModifiedPath\\\":\\\"\\\",\\\"LoadingOrder\\\":13,\\\"IsControlSpecific\\\":true},{\\\"Type\\\":5,\\\"Path\\\":\\\"/PCFControls/PowerApps_CoreControls_TextCanvas/strings/TextCanvas.1030.json\\\",\\\"ModifiedPath\\\":\\\"\\\",\\\"LoadingOrder\\\":13,\\\"IsControlSpecific\\\":true},{\\\"Type\\\":5,\\\"Path\\\":\\\"/PCFControls/PowerApps_CoreControls_TextCanvas/strings/TextCanvas.1031.json\\\",\\\"ModifiedPath\\\":\\\"\\\",\\\"LoadingOrder\\\":13,\\\"IsControlSpecific\\\":true},{\\\"Type\\\":5,\\\"Path\\\":\\\"/PCFControls/PowerApps_CoreControls_TextCanvas/strings/TextCanvas.1032.json\\\",\\\"ModifiedPath\\\":\\\"\\\",\\\"LoadingOrder\\\":13,\\\"IsControlSpecific\\\":true},{\\\"Type\\\":5,\\\"Path\\\":\\\"/PCFControls/PowerApps_CoreControls_TextCanvas/strings/TextCanvas.1033.json\\\",\\\"ModifiedPath\\\":\\\"\\\",\\\"LoadingOrder\\\":13,\\\"IsControlSpecific\\\":true},{\\\"Type\\\":5,\\\"Path\\\":\\\"/PCFControls/PowerApps_CoreControls_TextCanvas/strings/TextCanvas.1035.json\\\",\\\"ModifiedPath\\\":\\\"\\\",\\\"LoadingOrder\\\":13,\\\"IsControlSpecific\\\":true},{\\\"Type\\\":5,\\\"Path\\\":\\\"/PCFControls/PowerApps_CoreControls_TextCanvas/strings/TextCanvas.1036.json\\\",\\\"ModifiedPath\\\":\\\"\\\",\\\"LoadingOrder\\\":13,\\\"IsControlSpecific\\\":true},{\\\"Type\\\":5,\\\"Path\\\":\\\"/PCFControls/PowerApps_CoreControls_TextCanvas/strings/TextCanvas.1037.json\\\",\\\"ModifiedPath\\\":\\\"\\\",\\\"LoadingOrder\\\":13,\\\"IsControlSpecific\\\":true},{\\\"Type\\\":5,\\\"Path\\\":\\\"/PCFControls/PowerApps_CoreControls_TextCanvas/strings/TextCanvas.1038.json\\\",\\\"ModifiedPath\\\":\\\"\\\",\\\"LoadingOrder\\\":13,\\\"IsControlSpecific\\\":true},{\\\"Type\\\":5,\\\"Path\\\":\\\"/PCFControls/PowerApps_CoreControls_TextCanvas/strings/TextCanvas.1040.json\\\",\\\"ModifiedPath\\\":\\\"\\\",\\\"LoadingOrder\\\":13,\\\"IsControlSpecific\\\":true},{\\\"Type\\\":5,\\\"Path\\\":\\\"/PCFControls/PowerApps_CoreControls_TextCanvas/strings/TextCanvas.1041.json\\\",\\\"ModifiedPath\\\":\\\"\\\",\\\"LoadingOrder\\\":13,\\\"IsControlSpecific\\\":true},{\\\"Type\\\":5,\\\"Path\\\":\\\"/PCFControls/PowerApps_CoreControls_TextCanvas/strings/TextCanvas.1042.json\\\",\\\"ModifiedPath\\\":\\\"\\\",\\\"LoadingOrder\\\":13,\\\"IsControlSpecific\\\":true},{\\\"Type\\\":5,\\\"Path\\\":\\\"/PCFControls/PowerApps_CoreControls_TextCanvas/strings/TextCanvas.1043.json\\\",\\\"ModifiedPath\\\":\\\"\\\",\\\"LoadingOrder\\\":13,\\\"IsControlSpecific\\\":true},{\\\"Type\\\":5,\\\"Path\\\":\\\"/PCFControls/PowerApps_CoreControls_TextCanvas/strings/TextCanvas.1044.json\\\",\\\"ModifiedPath\\\":\\\"\\\",\\\"LoadingOrder\\\":13,\\\"IsControlSpecific\\\":true},{\\\"Type\\\":5,\\\"Path\\\":\\\"/PCFControls/PowerApps_CoreControls_TextCanvas/strings/TextCanvas.1045.json\\\",\\\"ModifiedPath\\\":\\\"\\\",\\\"LoadingOrder\\\":13,\\\"IsControlSpecific\\\":true},{\\\"Type\\\":5,\\\"Path\\\":\\\"/PCFControls/PowerApps_CoreControls_TextCanvas/strings/TextCanvas.1046.json\\\",\\\"ModifiedPath\\\":\\\"\\\",\\\"LoadingOrder\\\":13,\\\"IsControlSpecific\\\":true},{\\\"Type\\\":5,\\\"Path\\\":\\\"/PCFControls/PowerApps_CoreControls_TextCanvas/strings/TextCanvas.1048.json\\\",\\\"ModifiedPath\\\":\\\"\\\",\\\"LoadingOrder\\\":13,\\\"IsControlSpecific\\\":true},{\\\"Type\\\":5,\\\"Path\\\":\\\"/PCFControls/PowerApps_CoreControls_TextCanvas/strings/TextCanvas.1049.json\\\",\\\"ModifiedPath\\\":\\\"\\\",\\\"LoadingOrder\\\":13,\\\"IsControlSpecific\\\":true},{\\\"Type\\\":5,\\\"Path\\\":\\\"/PCFControls/PowerApps_CoreControls_TextCanvas/strings/TextCanvas.1050.json\\\",\\\"ModifiedPath\\\":\\\"\\\",\\\"LoadingOrder\\\":13,\\\"IsControlSpecific\\\":true},{\\\"Type\\\":5,\\\"Path\\\":\\\"/PCFControls/PowerApps_CoreControls_TextCanvas/strings/TextCanvas.1051.json\\\",\\\"ModifiedPath\\\":\\\"\\\",\\\"LoadingOrder\\\":13,\\\"IsControlSpecific\\\":true},{\\\"Type\\\":5,\\\"Path\\\":\\\"/PCFControls/PowerApps_CoreControls_TextCanvas/strings/TextCanvas.1053.json\\\",\\\"ModifiedPath\\\":\\\"\\\",\\\"LoadingOrder\\\":13,\\\"IsControlSpecific\\\":true},{\\\"Type\\\":5,\\\"Path\\\":\\\"/PCFControls/PowerApps_CoreControls_TextCanvas/strings/TextCanvas.1054.json\\\",\\\"ModifiedPath\\\":\\\"\\\",\\\"LoadingOrder\\\":13,\\\"IsControlSpecific\\\":true},{\\\"Type\\\":5,\\\"Path\\\":\\\"/PCFControls/PowerApps_CoreControls_TextCanvas/strings/TextCanvas.1055.json\\\",\\\"ModifiedPath\\\":\\\"\\\",\\\"LoadingOrder\\\":13,\\\"IsControlSpecific\\\":true},{\\\"Type\\\":5,\\\"Path\\\":\\\"/PCFControls/PowerApps_CoreControls_TextCanvas/strings/TextCanvas.1057.json\\\",\\\"ModifiedPath\\\":\\\"\\\",\\\"LoadingOrder\\\":13,\\\"IsControlSpecific\\\":true},{\\\"Type\\\":5,\\\"Path\\\":\\\"/PCFControls/PowerApps_CoreControls_TextCanvas/strings/TextCanvas.1058.json\\\",\\\"ModifiedPath\\\":\\\"\\\",\\\"LoadingOrder\\\":13,\\\"IsControlSpecific\\\":true},{\\\"Type\\\":5,\\\"Path\\\":\\\"/PCFControls/PowerApps_CoreControls_TextCanvas/strings/TextCanvas.1060.json\\\",\\\"ModifiedPath\\\":\\\"\\\",\\\"LoadingOrder\\\":13,\\\"IsControlSpecific\\\":true},{\\\"Type\\\":5,\\\"Path\\\":\\\"/PCFControls/PowerApps_CoreControls_TextCanvas/strings/TextCanvas.1061.json\\\",\\\"ModifiedPath\\\":\\\"\\\",\\\"LoadingOrder\\\":13,\\\"IsControlSpecific\\\":true},{\\\"Type\\\":5,\\\"Path\\\":\\\"/PCFControls/PowerApps_CoreControls_TextCanvas/strings/TextCanvas.1062.json\\\",\\\"ModifiedPath\\\":\\\"\\\",\\\"LoadingOrder\\\":13,\\\"IsControlSpecific\\\":true},{\\\"Type\\\":5,\\\"Path\\\":\\\"/PCFControls/PowerApps_CoreControls_TextCanvas/strings/TextCanvas.1063.json\\\",\\\"ModifiedPath\\\":\\\"\\\",\\\"LoadingOrder\\\":13,\\\"IsControlSpecific\\\":true},{\\\"Type\\\":5,\\\"Path\\\":\\\"/PCFControls/PowerApps_CoreControls_TextCanvas/strings/TextCanvas.1066.json\\\",\\\"ModifiedPath\\\":\\\"\\\",\\\"LoadingOrder\\\":13,\\\"IsControlSpecific\\\":true},{\\\"Type\\\":5,\\\"Path\\\":\\\"/PCFControls/PowerApps_CoreControls_TextCanvas/strings/TextCanvas.1069.json\\\",\\\"ModifiedPath\\\":\\\"\\\",\\\"LoadingOrder\\\":13,\\\"IsControlSpecific\\\":true},{\\\"Type\\\":5,\\\"Path\\\":\\\"/PCFControls/PowerApps_CoreControls_TextCanvas/strings/TextCanvas.1081.json\\\",\\\"ModifiedPath\\\":\\\"\\\",\\\"LoadingOrder\\\":13,\\\"IsControlSpecific\\\":true},{\\\"Type\\\":5,\\\"Path\\\":\\\"/PCFControls/PowerApps_CoreControls_TextCanvas/strings/TextCanvas.1086.json\\\",\\\"ModifiedPath\\\":\\\"\\\",\\\"LoadingOrder\\\":13,\\\"IsControlSpecific\\\":true},{\\\"Type\\\":5,\\\"Path\\\":\\\"/PCFControls/PowerApps_CoreControls_TextCanvas/strings/TextCanvas.1087.json\\\",\\\"ModifiedPath\\\":\\\"\\\",\\\"LoadingOrder\\\":13,\\\"IsControlSpecific\\\":true},{\\\"Type\\\":5,\\\"Path\\\":\\\"/PCFControls/PowerApps_CoreControls_TextCanvas/strings/TextCanvas.1110.json\\\",\\\"ModifiedPath\\\":\\\"\\\",\\\"LoadingOrder\\\":13,\\\"IsControlSpecific\\\":true},{\\\"Type\\\":5,\\\"Path\\\":\\\"/PCFControls/PowerApps_CoreControls_TextCanvas/strings/TextCanvas.2052.json\\\",\\\"ModifiedPath\\\":\\\"\\\",\\\"LoadingOrder\\\":13,\\\"IsControlSpecific\\\":true},{\\\"Type\\\":5,\\\"Path\\\":\\\"/PCFControls/PowerApps_CoreControls_TextCanvas/strings/TextCanvas.2070.json\\\",\\\"ModifiedPath\\\":\\\"\\\",\\\"LoadingOrder\\\":13,\\\"IsControlSpecific\\\":true},{\\\"Type\\\":5,\\\"Path\\\":\\\"/PCFControls/PowerApps_CoreControls_TextCanvas/strings/TextCanvas.2074.json\\\",\\\"ModifiedPath\\\":\\\"\\\",\\\"LoadingOrder\\\":13,\\\"IsControlSpecific\\\":true},{\\\"Type\\\":5,\\\"Path\\\":\\\"/PCFControls/PowerApps_CoreControls_TextCanvas/strings/TextCanvas.3076.json\\\",\\\"ModifiedPath\\\":\\\"\\\",\\\"LoadingOrder\\\":13,\\\"IsControlSpecific\\\":true},{\\\"Type\\\":5,\\\"Path\\\":\\\"/PCFControls/PowerApps_CoreControls_TextCanvas/strings/TextCanvas.3082.json\\\",\\\"ModifiedPath\\\":\\\"\\\",\\\"LoadingOrder\\\":13,\\\"IsControlSpecific\\\":true},{\\\"Type\\\":5,\\\"Path\\\":\\\"/PCFControls/PowerApps_CoreControls_TextCanvas/strings/TextCanvas.3098.json\\\",\\\"ModifiedPath\\\":\\\"\\\",\\\"LoadingOrder\\\":13,\\\"IsControlSpecific\\\":true},{\\\"Type\\\":3,\\\"Path\\\":\\\"{\\\\\\\"Id\\\\\\\":\\\\\\\"LocalizedStrings\\\\\\\",\\\\\\\"Data\\\\\\\":{\\\\\\\"LocStrings\\\\\\\":{\\\\\\\"TextCanvas\\\\\\\":\\\\\\\"Text\\\\\\\",\\\\\\\"TextCanvas_VerticalAlign\\\\\\\":\\\\\\\"Vertical align\\\\\\\",\\\\\\\"TextCanvas_VerticalAlign_Desc\\\\\\\":\\\\\\\"Display text using the selected text verlitcal alignment.\\\\\\\",\\\\\\\"TextCanvas_VerticalAlign_Top\\\\\\\":\\\\\\\"Top\\\\\\\",\\\\\\\"TextCanvas_VerticalAlign_Middle\\\\\\\":\\\\\\\"Middle\\\\\\\",\\\\\\\"TextCanvas_VerticalAlign_Bottom\\\\\\\":\\\\\\\"Bottom\\\\\\\",\\\\\\\"TextCanvas_Height\\\\\\\":\\\\\\\"Text height\\\\\\\",\\\\\\\"TextCanvas_Height_Desc\\\\\\\":\\\\\\\"The height of the control.\\\\\\\",\\\\\\\"TextCanvas_Align\\\\\\\":\\\\\\\"Align\\\\\\\",\\\\\\\"TextCanvas_Align_Desc\\\\\\\":\\\\\\\"Display text using the selected text alignment.\\\\\\\",\\\\\\\"TextCanvas_Align_Start\\\\\\\":\\\\\\\"Start\\\\\\\",\\\\\\\"TextCanvas_Align_End\\\\\\\":\\\\\\\"End\\\\\\\",\\\\\\\"TextCanvas_Align_Center\\\\\\\":\\\\\\\"Center\\\\\\\",\\\\\\\"TextCanvas_Align_Justify\\\\\\\":\\\\\\\"Justify\\\\\\\",\\\\\\\"TextCanvas_Desc\\\\\\\":\\\\\\\"Display text\\\\\\\",\\\\\\\"TextCanvas_AutoHeight\\\\\\\":\\\\\\\"Auto height\\\\\\\",\\\\\\\"TextCanvas_AutoHeight_Desc\\\\\\\":\\\\\\\"Container height will adjust to text content.\\\\\\\",\\\\\\\"TextCanvas_Italic\\\\\\\":\\\\\\\"Italic\\\\\\\",\\\\\\\"TextCanvas_Italic_Desc\\\\\\\":\\\\\\\"Display text using the italic font style.\\\\\\\",\\\\\\\"TextCanvas_Size\\\\\\\":\\\\\\\"Font size\\\\\\\",\\\\\\\"TextCanvas_Size_Desc\\\\\\\":\\\\\\\"Display text using the selected font sizes.\\\\\\\",\\\\\\\"TextCanvas_Strikethrough\\\\\\\":\\\\\\\"Strikethrough\\\\\\\",\\\\\\\"TextCanvas_Strikethrough_Desc\\\\\\\":\\\\\\\"Display text using the strikethrough font style.\\\\\\\",\\\\\\\"TextCanvas_Text\\\\\\\":\\\\\\\"Text\\\\\\\",\\\\\\\"TextCanvas_Text_Desc\\\\\\\":\\\\\\\"Text that appears on a control.\\\\\\\",\\\\\\\"TextCanvas_Underline\\\\\\\":\\\\\\\"Underline\\\\\\\",\\\\\\\"TextCanvas_Underline_Desc\\\\\\\":\\\\\\\"Display text using the underline font style.\\\\\\\",\\\\\\\"TextCanvas_Weight\\\\\\\":\\\\\\\"Font weight\\\\\\\",\\\\\\\"TextCanvas_Weight_Desc\\\\\\\":\\\\\\\"Display text using the selected font weights.\\\\\\\",\\\\\\\"TextCanvas_Weight_Medium\\\\\\\":\\\\\\\"Medium\\\\\\\",\\\\\\\"TextCanvas_Weight_Regular\\\\\\\":\\\\\\\"Regular\\\\\\\",\\\\\\\"TextCanvas_Weight_Semibold\\\\\\\":\\\\\\\"Semibold\\\\\\\",\\\\\\\"TextCanvas_Weight_Bold\\\\\\\":\\\\\\\"Bold\\\\\\\",\\\\\\\"TextCanvas_Wrap\\\\\\\":\\\\\\\"Wrap\\\\\\\",\\\\\\\"TextCanvas_Wrap_Desc\\\\\\\":\\\\\\\"Display overflow text as wrapped.\\\\\\\",\\\\\\\"Font\\\\\\\":\\\\\\\"Font\\\\\\\",\\\\\\\"Font_description\\\\\\\":\\\\\\\"The name of the family of fonts in which text appears\\\\\\\",\\\\\\\"Font_Color\\\\\\\":\\\\\\\"Font color\\\\\\\",\\\\\\\"Font_Color_description\\\\\\\":\\\\\\\"The color of text in the control\\\\\\\"}}}\\\",\\\"ModifiedPath\\\":\\\"\\\",\\\"LoadingOrder\\\":13,\\\"IsControlSpecific\\\":false},{\\\"Type\\\":0,\\\"Path\\\":\\\"/PCF/fluentui-react.js\\\",\\\"ModifiedPath\\\":\\\"\\\",\\\"LoadingOrder\\\":5,\\\"IsControlSpecific\\\":false},{\\\"Type\\\":4,\\\"Path\\\":\\\"Fluent/9.4.0/9.4.0\\\",\\\"ModifiedPath\\\":\\\"\\\",\\\"LoadingOrder\\\":0,\\\"IsControlSpecific\\\":false}]\",\"Properties\":\"[{\\\"Name\\\":\\\"Text\\\",\\\"DisplayName\\\":\\\"Text\\\",\\\"Description\\\":\\\"Text that appears on a control.\\\",\\\"Type\\\":6,\\\"Usage\\\":2,\\\"Hidden\\\":false,\\\"DefaultValue\\\":\\\"Text\\\",\\\"PfxDefaultValue\\\":\\\"\\\",\\\"PhoneDefaultValue\\\":\\\"\\\",\\\"WebDefaultValue\\\":\\\"\\\",\\\"NullDefaultValue\\\":null,\\\"HelperUI\\\":null,\\\"Category\\\":\\\"data\\\",\\\"IsPrimaryBehavioral\\\":false,\\\"IsPrimaryInput\\\":true,\\\"IsPrimaryOutput\\\":true,\\\"IsResettable\\\":false,\\\"EnumValues\\\":[],\\\"Required\\\":false,\\\"IsDataSourceProperty\\\":false,\\\"PassThroughProperty\\\":\\\"\\\",\\\"ShouldAutoBind\\\":true,\\\"ParentDataSetName\\\":\\\"\\\",\\\"DisplayNameResourceString\\\":\\\"TextCanvas_Text\\\",\\\"DescriptionResourceString\\\":\\\"TextCanvas_Text_Desc\\\",\\\"IsResettableToManifestDefault\\\":false,\\\"IsLinkableToParentTheme\\\":false},{\\\"Name\\\":\\\"Size\\\",\\\"DisplayName\\\":\\\"Font size\\\",\\\"Description\\\":\\\"Display text using the selected font sizes.\\\",\\\"Type\\\":16,\\\"Usage\\\":2,\\\"Hidden\\\":false,\\\"DefaultValue\\\":\\\"14\\\",\\\"PfxDefaultValue\\\":\\\"\\\",\\\"PhoneDefaultValue\\\":\\\"\\\",\\\"WebDefaultValue\\\":\\\"\\\",\\\"NullDefaultValue\\\":null,\\\"HelperUI\\\":null,\\\"Category\\\":\\\"data\\\",\\\"IsPrimaryBehavioral\\\":false,\\\"IsPrimaryInput\\\":false,\\\"IsPrimaryOutput\\\":false,\\\"IsResettable\\\":false,\\\"EnumValues\\\":[],\\\"Required\\\":false,\\\"IsDataSourceProperty\\\":false,\\\"PassThroughProperty\\\":\\\"\\\",\\\"ShouldAutoBind\\\":false,\\\"ParentDataSetName\\\":\\\"\\\",\\\"DisplayNameResourceString\\\":\\\"TextCanvas_Size\\\",\\\"DescriptionResourceString\\\":\\\"TextCanvas_Size_Desc\\\",\\\"IsResettableToManifestDefault\\\":false,\\\"IsLinkableToParentTheme\\\":false},{\\\"Name\\\":\\\"Weight\\\",\\\"DisplayName\\\":\\\"Font weight\\\",\\\"Description\\\":\\\"Display text using the selected font weights.\\\",\\\"Type\\\":1,\\\"Usage\\\":2,\\\"Hidden\\\":false,\\\"DefaultValue\\\":\\\"Regular\\\",\\\"PfxDefaultValue\\\":\\\"\\\",\\\"PhoneDefaultValue\\\":\\\"Regular\\\",\\\"WebDefaultValue\\\":\\\"Regular\\\",\\\"NullDefaultValue\\\":null,\\\"HelperUI\\\":null,\\\"Category\\\":\\\"data\\\",\\\"IsPrimaryBehavioral\\\":false,\\\"IsPrimaryInput\\\":false,\\\"IsPrimaryOutput\\\":false,\\\"IsResettable\\\":false,\\\"EnumValues\\\":[{\\\"Name\\\":\\\"Medium\\\",\\\"DisplayName\\\":\\\"Medium\\\",\\\"Description\\\":\\\"Medium\\\",\\\"IsDefaultValue\\\":false,\\\"Value\\\":\\\"Medium\\\"},{\\\"Name\\\":\\\"Regular\\\",\\\"DisplayName\\\":\\\"Regular\\\",\\\"Description\\\":\\\"Regular\\\",\\\"IsDefaultValue\\\":true,\\\"Value\\\":\\\"Regular\\\"},{\\\"Name\\\":\\\"Semibold\\\",\\\"DisplayName\\\":\\\"Semibold\\\",\\\"Description\\\":\\\"Semibold\\\",\\\"IsDefaultValue\\\":false,\\\"Value\\\":\\\"Semibold\\\"},{\\\"Name\\\":\\\"Bold\\\",\\\"DisplayName\\\":\\\"Bold\\\",\\\"Description\\\":\\\"Bold\\\",\\\"IsDefaultValue\\\":false,\\\"Value\\\":\\\"Bold\\\"}],\\\"Required\\\":false,\\\"IsDataSourceProperty\\\":false,\\\"PassThroughProperty\\\":\\\"\\\",\\\"ShouldAutoBind\\\":false,\\\"ParentDataSetName\\\":\\\"\\\",\\\"DisplayNameResourceString\\\":\\\"TextCanvas_Weight\\\",\\\"DescriptionResourceString\\\":\\\"TextCanvas_Weight_Desc\\\",\\\"IsResettableToManifestDefault\\\":false,\\\"IsLinkableToParentTheme\\\":false},{\\\"Name\\\":\\\"Align\\\",\\\"DisplayName\\\":\\\"Align\\\",\\\"Description\\\":\\\"Display text using the selected text alignment.\\\",\\\"Type\\\":1,\\\"Usage\\\":2,\\\"Hidden\\\":false,\\\"DefaultValue\\\":\\\"Start\\\",\\\"PfxDefaultValue\\\":\\\"\\\",\\\"PhoneDefaultValue\\\":\\\"Start\\\",\\\"WebDefaultValue\\\":\\\"Start\\\",\\\"NullDefaultValue\\\":null,\\\"HelperUI\\\":null,\\\"Category\\\":\\\"data\\\",\\\"IsPrimaryBehavioral\\\":false,\\\"IsPrimaryInput\\\":false,\\\"IsPrimaryOutput\\\":false,\\\"IsResettable\\\":false,\\\"EnumValues\\\":[{\\\"Name\\\":\\\"Start\\\",\\\"DisplayName\\\":\\\"Start\\\",\\\"Description\\\":\\\"Start\\\",\\\"IsDefaultValue\\\":true,\\\"Value\\\":\\\"Start\\\"},{\\\"Name\\\":\\\"End\\\",\\\"DisplayName\\\":\\\"End\\\",\\\"Description\\\":\\\"End\\\",\\\"IsDefaultValue\\\":false,\\\"Value\\\":\\\"End\\\"},{\\\"Name\\\":\\\"Center\\\",\\\"DisplayName\\\":\\\"Center\\\",\\\"Description\\\":\\\"Center\\\",\\\"IsDefaultValue\\\":false,\\\"Value\\\":\\\"Center\\\"},{\\\"Name\\\":\\\"Justify\\\",\\\"DisplayName\\\":\\\"Justify\\\",\\\"Description\\\":\\\"Justify\\\",\\\"IsDefaultValue\\\":false,\\\"Value\\\":\\\"Justify\\\"}],\\\"Required\\\":false,\\\"IsDataSourceProperty\\\":false,\\\"PassThroughProperty\\\":\\\"\\\",\\\"ShouldAutoBind\\\":false,\\\"ParentDataSetName\\\":\\\"\\\",\\\"DisplayNameResourceString\\\":\\\"TextCanvas_Align\\\",\\\"DescriptionResourceString\\\":\\\"TextCanvas_Align_Desc\\\",\\\"IsResettableToManifestDefault\\\":false,\\\"IsLinkableToParentTheme\\\":false},{\\\"Name\\\":\\\"VerticalAlign\\\",\\\"DisplayName\\\":\\\"Vertical align\\\",\\\"Description\\\":\\\"Display text using the selected text verlitcal alignment.\\\",\\\"Type\\\":1,\\\"Usage\\\":2,\\\"Hidden\\\":false,\\\"DefaultValue\\\":\\\"Middle\\\",\\\"PfxDefaultValue\\\":\\\"\\\",\\\"PhoneDefaultValue\\\":\\\"Middle\\\",\\\"WebDefaultValue\\\":\\\"Middle\\\",\\\"NullDefaultValue\\\":null,\\\"HelperUI\\\":null,\\\"Category\\\":\\\"data\\\",\\\"IsPrimaryBehavioral\\\":false,\\\"IsPrimaryInput\\\":false,\\\"IsPrimaryOutput\\\":false,\\\"IsResettable\\\":false,\\\"EnumValues\\\":[{\\\"Name\\\":\\\"Top\\\",\\\"DisplayName\\\":\\\"Top\\\",\\\"Description\\\":\\\"Top\\\",\\\"IsDefaultValue\\\":false,\\\"Value\\\":\\\"Top\\\"},{\\\"Name\\\":\\\"Middle\\\",\\\"DisplayName\\\":\\\"Middle\\\",\\\"Description\\\":\\\"Middle\\\",\\\"IsDefaultValue\\\":true,\\\"Value\\\":\\\"Middle\\\"},{\\\"Name\\\":\\\"Bottom\\\",\\\"DisplayName\\\":\\\"Bottom\\\",\\\"Description\\\":\\\"Bottom\\\",\\\"IsDefaultValue\\\":false,\\\"Value\\\":\\\"Bottom\\\"}],\\\"Required\\\":false,\\\"IsDataSourceProperty\\\":false,\\\"PassThroughProperty\\\":\\\"\\\",\\\"ShouldAutoBind\\\":false,\\\"ParentDataSetName\\\":\\\"\\\",\\\"DisplayNameResourceString\\\":\\\"TextCanvas_VerticalAlign\\\",\\\"DescriptionResourceString\\\":\\\"TextCanvas_VerticalAlign_Desc\\\",\\\"IsResettableToManifestDefault\\\":false,\\\"IsLinkableToParentTheme\\\":false},{\\\"Name\\\":\\\"AutoHeight\\\",\\\"DisplayName\\\":\\\"Auto height\\\",\\\"Description\\\":\\\"Container height will adjust to text content.\\\",\\\"Type\\\":20,\\\"Usage\\\":2,\\\"Hidden\\\":false,\\\"DefaultValue\\\":\\\"false\\\",\\\"PfxDefaultValue\\\":\\\"\\\",\\\"PhoneDefaultValue\\\":\\\"\\\",\\\"WebDefaultValue\\\":\\\"\\\",\\\"NullDefaultValue\\\":null,\\\"HelperUI\\\":null,\\\"Category\\\":\\\"data\\\",\\\"IsPrimaryBehavioral\\\":false,\\\"IsPrimaryInput\\\":false,\\\"IsPrimaryOutput\\\":false,\\\"IsResettable\\\":false,\\\"EnumValues\\\":[],\\\"Required\\\":false,\\\"IsDataSourceProperty\\\":false,\\\"PassThroughProperty\\\":\\\"\\\",\\\"ShouldAutoBind\\\":false,\\\"ParentDataSetName\\\":\\\"\\\",\\\"DisplayNameResourceString\\\":\\\"TextCanvas_AutoHeight\\\",\\\"DescriptionResourceString\\\":\\\"TextCanvas_AutoHeight_Desc\\\",\\\"IsResettableToManifestDefault\\\":false,\\\"IsLinkableToParentTheme\\\":false},{\\\"Name\\\":\\\"Height\\\",\\\"DisplayName\\\":\\\"Text height\\\",\\\"Description\\\":\\\"The height of the control.\\\",\\\"Type\\\":16,\\\"Usage\\\":2,\\\"Hidden\\\":false,\\\"DefaultValue\\\":\\\"32\\\",\\\"PfxDefaultValue\\\":\\\"\\\",\\\"PhoneDefaultValue\\\":\\\"\\\",\\\"WebDefaultValue\\\":\\\"\\\",\\\"NullDefaultValue\\\":null,\\\"HelperUI\\\":null,\\\"Category\\\":\\\"design\\\",\\\"IsPrimaryBehavioral\\\":false,\\\"IsPrimaryInput\\\":false,\\\"IsPrimaryOutput\\\":false,\\\"IsResettable\\\":false,\\\"EnumValues\\\":[],\\\"Required\\\":false,\\\"IsDataSourceProperty\\\":false,\\\"PassThroughProperty\\\":\\\"\\\",\\\"ShouldAutoBind\\\":false,\\\"ParentDataSetName\\\":\\\"\\\",\\\"DisplayNameResourceString\\\":\\\"TextCanvas_Height\\\",\\\"DescriptionResourceString\\\":\\\"TextCanvas_Height_Desc\\\",\\\"IsResettableToManifestDefault\\\":false,\\\"IsLinkableToParentTheme\\\":false},{\\\"Name\\\":\\\"Font\\\",\\\"DisplayName\\\":\\\"Font\\\",\\\"Description\\\":\\\"The name of the family of fonts in which text appears\\\",\\\"Type\\\":6,\\\"Usage\\\":0,\\\"Hidden\\\":false,\\\"DefaultValue\\\":\\\"\\\",\\\"PfxDefaultValue\\\":\\\"\\\",\\\"PhoneDefaultValue\\\":\\\"\\\",\\\"WebDefaultValue\\\":\\\"\\\",\\\"NullDefaultValue\\\":null,\\\"HelperUI\\\":null,\\\"Category\\\":\\\"data\\\",\\\"IsPrimaryBehavioral\\\":false,\\\"IsPrimaryInput\\\":false,\\\"IsPrimaryOutput\\\":false,\\\"IsResettable\\\":false,\\\"EnumValues\\\":[],\\\"Required\\\":false,\\\"IsDataSourceProperty\\\":false,\\\"PassThroughProperty\\\":\\\"\\\",\\\"ShouldAutoBind\\\":false,\\\"ParentDataSetName\\\":\\\"\\\",\\\"DisplayNameResourceString\\\":\\\"Font\\\",\\\"DescriptionResourceString\\\":\\\"Font_description\\\",\\\"IsResettableToManifestDefault\\\":true,\\\"IsLinkableToParentTheme\\\":true},{\\\"Name\\\":\\\"FontColor\\\",\\\"DisplayName\\\":\\\"Font color\\\",\\\"Description\\\":\\\"The color of text in the control\\\",\\\"Type\\\":6,\\\"Usage\\\":0,\\\"Hidden\\\":false,\\\"DefaultValue\\\":\\\"\\\",\\\"PfxDefaultValue\\\":\\\"\\\",\\\"PhoneDefaultValue\\\":\\\"\\\",\\\"WebDefaultValue\\\":\\\"\\\",\\\"NullDefaultValue\\\":null,\\\"HelperUI\\\":\\\"color\\\",\\\"Category\\\":\\\"data\\\",\\\"IsPrimaryBehavioral\\\":false,\\\"IsPrimaryInput\\\":false,\\\"IsPrimaryOutput\\\":false,\\\"IsResettable\\\":false,\\\"EnumValues\\\":[],\\\"Required\\\":false,\\\"IsDataSourceProperty\\\":false,\\\"PassThroughProperty\\\":\\\"\\\",\\\"ShouldAutoBind\\\":false,\\\"ParentDataSetName\\\":\\\"\\\",\\\"DisplayNameResourceString\\\":\\\"Font_Color\\\",\\\"DescriptionResourceString\\\":\\\"Font_Color_description\\\",\\\"IsResettableToManifestDefault\\\":true,\\\"IsLinkableToParentTheme\\\":true},{\\\"Name\\\":\\\"FontItalic\\\",\\\"DisplayName\\\":\\\"Italic\\\",\\\"Description\\\":\\\"Display text using the italic font style.\\\",\\\"Type\\\":20,\\\"Usage\\\":2,\\\"Hidden\\\":false,\\\"DefaultValue\\\":\\\"false\\\",\\\"PfxDefaultValue\\\":\\\"\\\",\\\"PhoneDefaultValue\\\":\\\"\\\",\\\"WebDefaultValue\\\":\\\"\\\",\\\"NullDefaultValue\\\":null,\\\"HelperUI\\\":null,\\\"Category\\\":\\\"data\\\",\\\"IsPrimaryBehavioral\\\":false,\\\"IsPrimaryInput\\\":false,\\\"IsPrimaryOutput\\\":false,\\\"IsResettable\\\":false,\\\"EnumValues\\\":[],\\\"Required\\\":false,\\\"IsDataSourceProperty\\\":false,\\\"PassThroughProperty\\\":\\\"\\\",\\\"ShouldAutoBind\\\":false,\\\"ParentDataSetName\\\":\\\"\\\",\\\"DisplayNameResourceString\\\":\\\"TextCanvas_Italic\\\",\\\"DescriptionResourceString\\\":\\\"TextCanvas_Italic_Desc\\\",\\\"IsResettableToManifestDefault\\\":false,\\\"IsLinkableToParentTheme\\\":false},{\\\"Name\\\":\\\"FontStrikethrough\\\",\\\"DisplayName\\\":\\\"Strikethrough\\\",\\\"Description\\\":\\\"Display text using the strikethrough font style.\\\",\\\"Type\\\":20,\\\"Usage\\\":2,\\\"Hidden\\\":false,\\\"DefaultValue\\\":\\\"false\\\",\\\"PfxDefaultValue\\\":\\\"\\\",\\\"PhoneDefaultValue\\\":\\\"\\\",\\\"WebDefaultValue\\\":\\\"\\\",\\\"NullDefaultValue\\\":null,\\\"HelperUI\\\":null,\\\"Category\\\":\\\"data\\\",\\\"IsPrimaryBehavioral\\\":false,\\\"IsPrimaryInput\\\":false,\\\"IsPrimaryOutput\\\":false,\\\"IsResettable\\\":false,\\\"EnumValues\\\":[],\\\"Required\\\":false,\\\"IsDataSourceProperty\\\":false,\\\"PassThroughProperty\\\":\\\"\\\",\\\"ShouldAutoBind\\\":false,\\\"ParentDataSetName\\\":\\\"\\\",\\\"DisplayNameResourceString\\\":\\\"TextCanvas_Strikethrough\\\",\\\"DescriptionResourceString\\\":\\\"TextCanvas_Strikethrough_Desc\\\",\\\"IsResettableToManifestDefault\\\":false,\\\"IsLinkableToParentTheme\\\":false},{\\\"Name\\\":\\\"FontUnderline\\\",\\\"DisplayName\\\":\\\"Underline\\\",\\\"Description\\\":\\\"Display text using the underline font style.\\\",\\\"Type\\\":20,\\\"Usage\\\":2,\\\"Hidden\\\":false,\\\"DefaultValue\\\":\\\"false\\\",\\\"PfxDefaultValue\\\":\\\"\\\",\\\"PhoneDefaultValue\\\":\\\"\\\",\\\"WebDefaultValue\\\":\\\"\\\",\\\"NullDefaultValue\\\":null,\\\"HelperUI\\\":null,\\\"Category\\\":\\\"data\\\",\\\"IsPrimaryBehavioral\\\":false,\\\"IsPrimaryInput\\\":false,\\\"IsPrimaryOutput\\\":false,\\\"IsResettable\\\":false,\\\"EnumValues\\\":[],\\\"Required\\\":false,\\\"IsDataSourceProperty\\\":false,\\\"PassThroughProperty\\\":\\\"\\\",\\\"ShouldAutoBind\\\":false,\\\"ParentDataSetName\\\":\\\"\\\",\\\"DisplayNameResourceString\\\":\\\"TextCanvas_Underline\\\",\\\"DescriptionResourceString\\\":\\\"TextCanvas_Underline_Desc\\\",\\\"IsResettableToManifestDefault\\\":false,\\\"IsLinkableToParentTheme\\\":false},{\\\"Name\\\":\\\"Wrap\\\",\\\"DisplayName\\\":\\\"Wrap\\\",\\\"Description\\\":\\\"Display overflow text as wrapped.\\\",\\\"Type\\\":20,\\\"Usage\\\":2,\\\"Hidden\\\":false,\\\"DefaultValue\\\":\\\"true\\\",\\\"PfxDefaultValue\\\":\\\"\\\",\\\"PhoneDefaultValue\\\":\\\"\\\",\\\"WebDefaultValue\\\":\\\"\\\",\\\"NullDefaultValue\\\":null,\\\"HelperUI\\\":null,\\\"Category\\\":\\\"data\\\",\\\"IsPrimaryBehavioral\\\":false,\\\"IsPrimaryInput\\\":false,\\\"IsPrimaryOutput\\\":false,\\\"IsResettable\\\":false,\\\"EnumValues\\\":[],\\\"Required\\\":false,\\\"IsDataSourceProperty\\\":false,\\\"PassThroughProperty\\\":\\\"\\\",\\\"ShouldAutoBind\\\":false,\\\"ParentDataSetName\\\":\\\"\\\",\\\"DisplayNameResourceString\\\":\\\"TextCanvas_Wrap\\\",\\\"DescriptionResourceString\\\":\\\"TextCanvas_Wrap_Desc\\\",\\\"IsResettableToManifestDefault\\\":false,\\\"IsLinkableToParentTheme\\\":false},{\\\"Name\\\":\\\"TabIndex\\\",\\\"DisplayName\\\":\\\"NA\\\",\\\"Description\\\":\\\"NA\\\",\\\"Type\\\":16,\\\"Usage\\\":0,\\\"Hidden\\\":true,\\\"DefaultValue\\\":\\\"\\\",\\\"PfxDefaultValue\\\":\\\"\\\",\\\"PhoneDefaultValue\\\":\\\"\\\",\\\"WebDefaultValue\\\":\\\"\\\",\\\"NullDefaultValue\\\":null,\\\"HelperUI\\\":\\\"\\\",\\\"Category\\\":\\\"design\\\",\\\"IsPrimaryBehavioral\\\":false,\\\"IsPrimaryInput\\\":false,\\\"IsPrimaryOutput\\\":false,\\\"IsResettable\\\":false,\\\"EnumValues\\\":[],\\\"Required\\\":false,\\\"IsDataSourceProperty\\\":false,\\\"PassThroughProperty\\\":\\\"\\\",\\\"ShouldAutoBind\\\":false,\\\"ParentDataSetName\\\":\\\"\\\",\\\"DisplayNameResourceString\\\":\\\"NA\\\",\\\"DescriptionResourceString\\\":\\\"NA\\\",\\\"IsResettableToManifestDefault\\\":false,\\\"IsLinkableToParentTheme\\\":false},{\\\"Name\\\":\\\"Tooltip\\\",\\\"DisplayName\\\":\\\"NA\\\",\\\"Description\\\":\\\"NA\\\",\\\"Type\\\":6,\\\"Usage\\\":0,\\\"Hidden\\\":true,\\\"DefaultValue\\\":\\\"\\\",\\\"PfxDefaultValue\\\":\\\"\\\",\\\"PhoneDefaultValue\\\":\\\"\\\",\\\"WebDefaultValue\\\":\\\"\\\",\\\"NullDefaultValue\\\":null,\\\"HelperUI\\\":\\\"\\\",\\\"Category\\\":\\\"design\\\",\\\"IsPrimaryBehavioral\\\":false,\\\"IsPrimaryInput\\\":false,\\\"IsPrimaryOutput\\\":false,\\\"IsResettable\\\":false,\\\"EnumValues\\\":[],\\\"Required\\\":false,\\\"IsDataSourceProperty\\\":false,\\\"PassThroughProperty\\\":\\\"\\\",\\\"ShouldAutoBind\\\":false,\\\"ParentDataSetName\\\":\\\"\\\",\\\"DisplayNameResourceString\\\":\\\"NA\\\",\\\"DescriptionResourceString\\\":\\\"NA\\\",\\\"IsResettableToManifestDefault\\\":false,\\\"IsLinkableToParentTheme\\\":false},{\\\"Name\\\":\\\"PCFTeamsTheme\\\",\\\"DisplayName\\\":\\\"PCFTeamsTheme\\\",\\\"Description\\\":\\\"\\\",\\\"Type\\\":3,\\\"Usage\\\":0,\\\"Hidden\\\":true,\\\"DefaultValue\\\":\\\"\\\",\\\"PfxDefaultValue\\\":\\\"\\\",\\\"PhoneDefaultValue\\\":\\\"\\\",\\\"WebDefaultValue\\\":\\\"\\\",\\\"NullDefaultValue\\\":\\\"\\\",\\\"HelperUI\\\":\\\"\\\",\\\"Category\\\":\\\"design\\\",\\\"IsPrimaryBehavioral\\\":false,\\\"IsPrimaryInput\\\":false,\\\"IsPrimaryOutput\\\":false,\\\"IsResettable\\\":false,\\\"EnumValues\\\":null,\\\"Required\\\":false,\\\"IsDataSourceProperty\\\":false,\\\"PassThroughProperty\\\":\\\"\\\",\\\"ShouldAutoBind\\\":false,\\\"ParentDataSetName\\\":\\\"\\\",\\\"DisplayNameResourceString\\\":\\\"\\\",\\\"DescriptionResourceString\\\":\\\"\\\",\\\"IsResettableToManifestDefault\\\":false,\\\"IsLinkableToParentTheme\\\":false}]\",\"IncludedProperties\":\"[{\\\"Name\\\":\\\"X\\\",\\\"DisplayName\\\":\\\"CC_X\\\",\\\"Description\\\":\\\"\\\",\\\"Type\\\":2,\\\"Usage\\\":2,\\\"Hidden\\\":false,\\\"DefaultValue\\\":\\\"\\\",\\\"PfxDefaultValue\\\":null,\\\"PhoneDefaultValue\\\":\\\"\\\",\\\"WebDefaultValue\\\":\\\"\\\",\\\"NullDefaultValue\\\":\\\"\\\",\\\"HelperUI\\\":\\\"\\\",\\\"Category\\\":\\\"design\\\",\\\"IsPrimaryBehavioral\\\":false,\\\"IsPrimaryInput\\\":false,\\\"IsPrimaryOutput\\\":false,\\\"IsResettable\\\":false,\\\"EnumValues\\\":null,\\\"Required\\\":false,\\\"IsDataSourceProperty\\\":false,\\\"PassThroughProperty\\\":\\\"\\\",\\\"ShouldAutoBind\\\":false,\\\"ParentDataSetName\\\":\\\"\\\",\\\"DisplayNameResourceString\\\":\\\"CC_X\\\",\\\"DescriptionResourceString\\\":\\\"\\\",\\\"IsResettableToManifestDefault\\\":false,\\\"IsLinkableToParentTheme\\\":false},{\\\"Name\\\":\\\"Y\\\",\\\"DisplayName\\\":\\\"CC_Y\\\",\\\"Description\\\":\\\"\\\",\\\"Type\\\":2,\\\"Usage\\\":2,\\\"Hidden\\\":false,\\\"DefaultValue\\\":\\\"\\\",\\\"PfxDefaultValue\\\":null,\\\"PhoneDefaultValue\\\":\\\"\\\",\\\"WebDefaultValue\\\":\\\"\\\",\\\"NullDefaultValue\\\":\\\"\\\",\\\"HelperUI\\\":\\\"\\\",\\\"Category\\\":\\\"design\\\",\\\"IsPrimaryBehavioral\\\":false,\\\"IsPrimaryInput\\\":false,\\\"IsPrimaryOutput\\\":false,\\\"IsResettable\\\":false,\\\"EnumValues\\\":null,\\\"Required\\\":false,\\\"IsDataSourceProperty\\\":false,\\\"PassThroughProperty\\\":\\\"\\\",\\\"ShouldAutoBind\\\":false,\\\"ParentDataSetName\\\":\\\"\\\",\\\"DisplayNameResourceString\\\":\\\"CC_Y\\\",\\\"DescriptionResourceString\\\":\\\"\\\",\\\"IsResettableToManifestDefault\\\":false,\\\"IsLinkableToParentTheme\\\":false},{\\\"Name\\\":\\\"Width\\\",\\\"DisplayName\\\":\\\"Width\\\",\\\"Description\\\":\\\"\\\",\\\"Type\\\":2,\\\"Usage\\\":2,\\\"Hidden\\\":false,\\\"DefaultValue\\\":\\\"96\\\",\\\"PfxDefaultValue\\\":null,\\\"PhoneDefaultValue\\\":\\\"96\\\",\\\"WebDefaultValue\\\":\\\"96\\\",\\\"NullDefaultValue\\\":\\\"0\\\",\\\"HelperUI\\\":\\\"\\\",\\\"Category\\\":\\\"design\\\",\\\"IsPrimaryBehavioral\\\":false,\\\"IsPrimaryInput\\\":false,\\\"IsPrimaryOutput\\\":false,\\\"IsResettable\\\":false,\\\"EnumValues\\\":null,\\\"Required\\\":false,\\\"IsDataSourceProperty\\\":false,\\\"PassThroughProperty\\\":\\\"\\\",\\\"ShouldAutoBind\\\":false,\\\"ParentDataSetName\\\":\\\"\\\",\\\"DisplayNameResourceString\\\":\\\"Width\\\",\\\"DescriptionResourceString\\\":\\\"\\\",\\\"IsResettableToManifestDefault\\\":false,\\\"IsLinkableToParentTheme\\\":false},{\\\"Name\\\":\\\"Visible\\\",\\\"DisplayName\\\":\\\"Visible\\\",\\\"Description\\\":\\\"\\\",\\\"Type\\\":4,\\\"Usage\\\":2,\\\"Hidden\\\":false,\\\"DefaultValue\\\":\\\"true\\\",\\\"PfxDefaultValue\\\":null,\\\"PhoneDefaultValue\\\":\\\"\\\",\\\"WebDefaultValue\\\":\\\"\\\",\\\"NullDefaultValue\\\":\\\"\\\",\\\"HelperUI\\\":\\\"\\\",\\\"Category\\\":\\\"design\\\",\\\"IsPrimaryBehavioral\\\":false,\\\"IsPrimaryInput\\\":false,\\\"IsPrimaryOutput\\\":false,\\\"IsResettable\\\":false,\\\"EnumValues\\\":null,\\\"Required\\\":false,\\\"IsDataSourceProperty\\\":false,\\\"PassThroughProperty\\\":\\\"\\\",\\\"ShouldAutoBind\\\":false,\\\"ParentDataSetName\\\":\\\"\\\",\\\"DisplayNameResourceString\\\":\\\"Visible\\\",\\\"DescriptionResourceString\\\":\\\"\\\",\\\"IsResettableToManifestDefault\\\":false,\\\"IsLinkableToParentTheme\\\":false},{\\\"Name\\\":\\\"DisplayMode\\\",\\\"DisplayName\\\":\\\"DisplayMode\\\",\\\"Description\\\":\\\"\\\",\\\"Type\\\":27,\\\"Usage\\\":2,\\\"Hidden\\\":false,\\\"DefaultValue\\\":\\\"\\\",\\\"PfxDefaultValue\\\":null,\\\"PhoneDefaultValue\\\":\\\"\\\",\\\"WebDefaultValue\\\":\\\"\\\",\\\"NullDefaultValue\\\":\\\"\\\",\\\"HelperUI\\\":\\\"\\\",\\\"Category\\\":\\\"design\\\",\\\"IsPrimaryBehavioral\\\":false,\\\"IsPrimaryInput\\\":false,\\\"IsPrimaryOutput\\\":false,\\\"IsResettable\\\":false,\\\"EnumValues\\\":null,\\\"Required\\\":false,\\\"IsDataSourceProperty\\\":false,\\\"PassThroughProperty\\\":\\\"\\\",\\\"ShouldAutoBind\\\":false,\\\"ParentDataSetName\\\":\\\"\\\",\\\"DisplayNameResourceString\\\":\\\"DisplayMode\\\",\\\"DescriptionResourceString\\\":\\\"\\\",\\\"IsResettableToManifestDefault\\\":false,\\\"IsLinkableToParentTheme\\\":false}]\",\"AuthConfigProperties\":\"[{\\\"Text\\\":{\\\"SectionIndex\\\":0,\\\"HelperUI\\\":null,\\\"PropertyGroupName\\\":\\\"\\\",\\\"SectionName\\\":null,\\\"Type\\\":0,\\\"PropertyKind\\\":1,\\\"WizardStep\\\":null,\\\"EnabledForFlyout\\\":false,\\\"Hidden\\\":false,\\\"SectionType\\\":\\\"GeneralSection\\\",\\\"ShowInCanvasInlineActionBar\\\":false},\\\"Visible\\\":{\\\"SectionIndex\\\":0,\\\"HelperUI\\\":null,\\\"PropertyGroupName\\\":\\\"\\\",\\\"SectionName\\\":null,\\\"Type\\\":0,\\\"PropertyKind\\\":1,\\\"WizardStep\\\":null,\\\"EnabledForFlyout\\\":false,\\\"Hidden\\\":false,\\\"SectionType\\\":\\\"GeneralSection\\\",\\\"ShowInCanvasInlineActionBar\\\":false},\\\"Wrap\\\":{\\\"SectionIndex\\\":1,\\\"HelperUI\\\":null,\\\"PropertyGroupName\\\":\\\"\\\",\\\"SectionName\\\":null,\\\"Type\\\":0,\\\"PropertyKind\\\":1,\\\"WizardStep\\\":null,\\\"EnabledForFlyout\\\":false,\\\"Hidden\\\":false,\\\"SectionType\\\":\\\"BehaviorSection\\\",\\\"ShowInCanvasInlineActionBar\\\":false},\\\"Align\\\":{\\\"SectionIndex\\\":2,\\\"HelperUI\\\":null,\\\"PropertyGroupName\\\":\\\"\\\",\\\"SectionName\\\":null,\\\"Type\\\":0,\\\"PropertyKind\\\":1,\\\"WizardStep\\\":null,\\\"EnabledForFlyout\\\":false,\\\"Hidden\\\":false,\\\"SectionType\\\":\\\"SizeAndPositioningSection\\\",\\\"ShowInCanvasInlineActionBar\\\":false},\\\"VerticalAlign\\\":{\\\"SectionIndex\\\":2,\\\"HelperUI\\\":null,\\\"PropertyGroupName\\\":\\\"\\\",\\\"SectionName\\\":null,\\\"Type\\\":0,\\\"PropertyKind\\\":1,\\\"WizardStep\\\":null,\\\"EnabledForFlyout\\\":false,\\\"Hidden\\\":false,\\\"SectionType\\\":\\\"SizeAndPositioningSection\\\",\\\"ShowInCanvasInlineActionBar\\\":false},\\\"AutoHeight\\\":{\\\"SectionIndex\\\":2,\\\"HelperUI\\\":null,\\\"PropertyGroupName\\\":\\\"\\\",\\\"SectionName\\\":null,\\\"Type\\\":0,\\\"PropertyKind\\\":1,\\\"WizardStep\\\":null,\\\"EnabledForFlyout\\\":false,\\\"Hidden\\\":false,\\\"SectionType\\\":\\\"SizeAndPositioningSection\\\",\\\"ShowInCanvasInlineActionBar\\\":false},\\\"X\\\":{\\\"SectionIndex\\\":2,\\\"HelperUI\\\":null,\\\"PropertyGroupName\\\":\\\"Position\\\",\\\"SectionName\\\":null,\\\"Type\\\":0,\\\"PropertyKind\\\":2,\\\"WizardStep\\\":null,\\\"EnabledForFlyout\\\":false,\\\"Hidden\\\":false,\\\"SectionType\\\":\\\"SizeAndPositioningSection\\\",\\\"ShowInCanvasInlineActionBar\\\":false},\\\"Y\\\":{\\\"SectionIndex\\\":2,\\\"HelperUI\\\":null,\\\"PropertyGroupName\\\":\\\"Position\\\",\\\"SectionName\\\":null,\\\"Type\\\":0,\\\"PropertyKind\\\":2,\\\"WizardStep\\\":null,\\\"EnabledForFlyout\\\":false,\\\"Hidden\\\":false,\\\"SectionType\\\":\\\"SizeAndPositioningSection\\\",\\\"ShowInCanvasInlineActionBar\\\":false},\\\"Width\\\":{\\\"SectionIndex\\\":2,\\\"HelperUI\\\":null,\\\"PropertyGroupName\\\":\\\"Size\\\",\\\"SectionName\\\":null,\\\"Type\\\":0,\\\"PropertyKind\\\":2,\\\"WizardStep\\\":null,\\\"EnabledForFlyout\\\":false,\\\"Hidden\\\":false,\\\"SectionType\\\":\\\"SizeAndPositioningSection\\\",\\\"ShowInCanvasInlineActionBar\\\":false},\\\"Height\\\":{\\\"SectionIndex\\\":2,\\\"HelperUI\\\":null,\\\"PropertyGroupName\\\":\\\"Size\\\",\\\"SectionName\\\":null,\\\"Type\\\":0,\\\"PropertyKind\\\":2,\\\"WizardStep\\\":null,\\\"EnabledForFlyout\\\":false,\\\"Hidden\\\":false,\\\"SectionType\\\":\\\"SizeAndPositioningSection\\\",\\\"ShowInCanvasInlineActionBar\\\":false},\\\"Font\\\":{\\\"SectionIndex\\\":3,\\\"HelperUI\\\":null,\\\"PropertyGroupName\\\":\\\"\\\",\\\"SectionName\\\":null,\\\"Type\\\":33,\\\"PropertyKind\\\":1,\\\"WizardStep\\\":null,\\\"EnabledForFlyout\\\":false,\\\"Hidden\\\":false,\\\"SectionType\\\":\\\"StyleAndThemeSection\\\",\\\"ShowInCanvasInlineActionBar\\\":false},\\\"Size\\\":{\\\"SectionIndex\\\":3,\\\"HelperUI\\\":null,\\\"PropertyGroupName\\\":\\\"\\\",\\\"SectionName\\\":null,\\\"Type\\\":0,\\\"PropertyKind\\\":1,\\\"WizardStep\\\":null,\\\"EnabledForFlyout\\\":false,\\\"Hidden\\\":false,\\\"SectionType\\\":\\\"StyleAndThemeSection\\\",\\\"ShowInCanvasInlineActionBar\\\":false},\\\"FontColor\\\":{\\\"SectionIndex\\\":3,\\\"HelperUI\\\":\\\"color\\\",\\\"PropertyGroupName\\\":\\\"\\\",\\\"SectionName\\\":null,\\\"Type\\\":31,\\\"PropertyKind\\\":1,\\\"WizardStep\\\":null,\\\"EnabledForFlyout\\\":false,\\\"Hidden\\\":false,\\\"SectionType\\\":\\\"StyleAndThemeSection\\\",\\\"ShowInCanvasInlineActionBar\\\":false},\\\"Weight\\\":{\\\"SectionIndex\\\":3,\\\"HelperUI\\\":null,\\\"PropertyGroupName\\\":\\\"\\\",\\\"SectionName\\\":null,\\\"Type\\\":0,\\\"PropertyKind\\\":1,\\\"WizardStep\\\":null,\\\"EnabledForFlyout\\\":false,\\\"Hidden\\\":false,\\\"SectionType\\\":\\\"StyleAndThemeSection\\\",\\\"ShowInCanvasInlineActionBar\\\":false},\\\"FontItalic\\\":{\\\"SectionIndex\\\":3,\\\"HelperUI\\\":null,\\\"PropertyGroupName\\\":\\\"Style\\\",\\\"SectionName\\\":null,\\\"Type\\\":35,\\\"PropertyKind\\\":2,\\\"WizardStep\\\":null,\\\"EnabledForFlyout\\\":false,\\\"Hidden\\\":false,\\\"SectionType\\\":\\\"StyleAndThemeSection\\\",\\\"ShowInCanvasInlineActionBar\\\":false},\\\"FontUnderline\\\":{\\\"SectionIndex\\\":3,\\\"HelperUI\\\":null,\\\"PropertyGroupName\\\":\\\"Style\\\",\\\"SectionName\\\":null,\\\"Type\\\":36,\\\"PropertyKind\\\":2,\\\"WizardStep\\\":null,\\\"EnabledForFlyout\\\":false,\\\"Hidden\\\":false,\\\"SectionType\\\":\\\"StyleAndThemeSection\\\",\\\"ShowInCanvasInlineActionBar\\\":false},\\\"FontStrikethrough\\\":{\\\"SectionIndex\\\":3,\\\"HelperUI\\\":null,\\\"PropertyGroupName\\\":\\\"Style\\\",\\\"SectionName\\\":null,\\\"Type\\\":37,\\\"PropertyKind\\\":2,\\\"WizardStep\\\":null,\\\"EnabledForFlyout\\\":false,\\\"Hidden\\\":false,\\\"SectionType\\\":\\\"StyleAndThemeSection\\\",\\\"ShowInCanvasInlineActionBar\\\":false}}]\"}",
              "FirstParty": true,
              "Id": "http://microsoft.com/appmagic/powercontrol/PowerApps_CoreControls_TextCanvas",
              "IsComponentDefinition": false,
              "IsCustomGroupControlTemplate": false,
              "IsPremiumPcfControl": false,
              "LastModifiedTimestamp": "0",
              "Name": "PowerApps_CoreControls_TextCanvas",
              "OverridableProperties": {},
              "TemplateDisplayName": "Text",
              "Version": "0.0.25"
            },
            "Type": "ControlInfo",
            "VariantName": ""
          }
        ],
        "ControlPropertyState": [
          "BorderColor",
          "BorderStyle",
          "Fill",
          "X",
          "Y",
          "Width",
          {
            "AFDDataSourceName": "",
            "AutoRuleBindingEnabled": false,
            "AutoRuleBindingString": "200",
            "InvariantPropertyName": "Height",
            "IsLockable": false,
            "NameMapSourceSchema": "?"
          },
          "DisplayMode",
          "ChildTabPriority",
          "LayoutMode",
          "LayoutDirection",
          "LayoutAlignItems",
          "LayoutJustifyContent",
          "LayoutGap",
          "LayoutOverflowX",
          "LayoutOverflowY",
          "LayoutWrap",
          "DropShadow",
          "ZIndex",
          "RadiusTopLeft",
          "RadiusTopRight",
          "RadiusBottomLeft",
          "RadiusBottomRight"
        ],
        "ControlUniqueId": "513",
        "HasDynamicProperties": false,
        "Index": 0,
        "IsAutoGenerated": false,
        "IsDataControl": false,
        "IsFromScreenLayout": false,
        "IsGroupControl": false,
        "IsLocked": false,
        "LayoutName": "",
        "MetaDataIDKey": "",
        "Name": "Container10",
        "OptimizeForDevices": "Off",
        "Parent": "PageInfo",
        "PersistMetaDataIDKey": false,
        "PublishOrderIndex": 0,
        "Rules": [
          {
            "Category": "Design",
            "InvariantScript": "RGBA(0, 0, 0, 1)",
            "Property": "BorderColor",
            "RuleProviderType": "Unknown"
          },
          {
            "Category": "Design",
            "InvariantScript": "BorderStyle.Solid",
            "Property": "BorderStyle",
            "RuleProviderType": "Unknown"
          },
          {
            "Category": "Design",
            "InvariantScript": "RGBA(0, 0, 0, 0)",
            "Property": "Fill",
            "RuleProviderType": "Unknown"
          },
          {
            "Category": "Design",
            "InvariantScript": "0",
            "Property": "X",
            "RuleProviderType": "Unknown"
          },
          {
            "Category": "Design",
            "InvariantScript": "40",
            "Property": "Y",
            "RuleProviderType": "Unknown"
          },
          {
            "Category": "Design",
            "InvariantScript": "1366",
            "Property": "Width",
            "RuleProviderType": "Unknown"
          },
          {
            "Category": "Design",
            "InvariantScript": "40",
            "Property": "Height",
            "RuleProviderType": "User"
          },
          {
            "Category": "Design",
            "InvariantScript": "DisplayMode.Edit",
            "Property": "DisplayMode",
            "RuleProviderType": "Unknown"
          },
          {
            "Category": "Design",
            "InvariantScript": "true",
            "Property": "ChildTabPriority",
            "RuleProviderType": "Unknown"
          },
          {
            "Category": "Design",
            "InvariantScript": "LayoutMode.Auto",
            "Property": "LayoutMode",
            "RuleProviderType": "Unknown"
          },
          {
            "Category": "Design",
            "InvariantScript": "LayoutDirection.Horizontal",
            "Property": "LayoutDirection",
            "RuleProviderType": "Unknown"
          },
          {
            "Category": "Design",
            "InvariantScript": "LayoutAlignItems.Start",
            "Property": "LayoutAlignItems",
            "RuleProviderType": "Unknown"
          },
          {
            "Category": "Design",
            "InvariantScript": "LayoutJustifyContent.Start",
            "Property": "LayoutJustifyContent",
            "RuleProviderType": "Unknown"
          },
          {
            "Category": "Design",
            "InvariantScript": "0",
            "Property": "LayoutGap",
            "RuleProviderType": "Unknown"
          },
          {
            "Category": "Design",
            "InvariantScript": "LayoutOverflow.Hide",
            "Property": "LayoutOverflowX",
            "RuleProviderType": "Unknown"
          },
          {
            "Category": "Design",
            "InvariantScript": "LayoutOverflow.Hide",
            "Property": "LayoutOverflowY",
            "RuleProviderType": "Unknown"
          },
          {
            "Category": "Design",
            "InvariantScript": "false",
            "Property": "LayoutWrap",
            "RuleProviderType": "Unknown"
          },
          {
            "Category": "Design",
            "InvariantScript": "DropShadow.Light",
            "Property": "DropShadow",
            "RuleProviderType": "Unknown"
          },
          {
            "Category": "Design",
            "InvariantScript": "1",
            "Property": "ZIndex",
            "RuleProviderType": "Unknown"
          },
          {
            "Category": "Design",
            "InvariantScript": "4",
            "Property": "RadiusTopLeft",
            "RuleProviderType": "Unknown"
          },
          {
            "Category": "Design",
            "InvariantScript": "4",
            "Property": "RadiusTopRight",
            "RuleProviderType": "Unknown"
          },
          {
            "Category": "Design",
            "InvariantScript": "4",
            "Property": "RadiusBottomLeft",
            "RuleProviderType": "Unknown"
          },
          {
            "Category": "Design",
            "InvariantScript": "4",
            "Property": "RadiusBottomRight",
            "RuleProviderType": "Unknown"
          }
        ],
        "StyleName": "defaultGroupContainerStyle",
        "Template": {
          "CustomGroupControlTemplateName": "",
          "FirstParty": true,
          "Id": "http://microsoft.com/appmagic/groupContainer",
          "IsComponentDefinition": false,
          "IsCustomGroupControlTemplate": false,
          "IsPremiumPcfControl": false,
          "LastModifiedTimestamp": "0",
          "Name": "groupContainer",
          "OverridableProperties": {},
          "Version": "1.3.0"
        },
        "Type": "ControlInfo",
        "VariantName": "horizontalAutoLayoutContainer"
      }
    ],
    "ControlPropertyState": [
      "Fill",
      {
        "AFDDataSourceName": "",
        "AutoRuleBindingEnabled": false,
        "AutoRuleBindingString": "",
        "InvariantPropertyName": "Height",
        "IsLockable": false,
        "NameMapSourceSchema": "?"
      },
      {
        "AFDDataSourceName": "",
        "AutoRuleBindingEnabled": false,
        "AutoRuleBindingString": "640",
        "InvariantPropertyName": "Width",
        "IsLockable": false,
        "NameMapSourceSchema": "?"
      },
      "X",
      "Y",
      "ZIndex",
      "Title"
    ],
    "LastModifiedTimestamp": "638525881219587964",
    "Name": "PageInfo",
    "Rules": [
      {
        "Category": "Data",
        "InvariantScript": "\"Text\"",
        "Property": "Title",
        "RuleProviderType": "System"
      },
      {
        "Category": "Design",
        "InvariantScript": "RGBA(0, 0, 0, 0)",
        "Property": "Fill",
        "RuleProviderType": "System"
      },
      {
        "Category": "Design",
        "InvariantScript": "40",
        "Property": "Height",
        "RuleProviderType": "System"
      },
      {
        "Category": "Design",
        "InvariantScript": "Max(App.Width, App.MinScreenWidth)",
        "Property": "Width",
        "RuleProviderType": "System"
      },
      {
        "Category": "Design",
        "InvariantScript": "0",
        "Property": "X",
        "RuleProviderType": "System"
      },
      {
        "Category": "Design",
        "InvariantScript": "0",
        "Property": "Y",
        "RuleProviderType": "System"
      },
      {
        "Category": "Design",
        "InvariantScript": "1",
        "Property": "ZIndex",
        "RuleProviderType": "System"
      }
    ]
  },
  "ComponentManifest": {
    "AllowAccessToGlobals": false,
    "AllowCustomization": true,
    "Description": "",
    "Name": "PageInfo",
    "TemplateGuid": "9a182439b559408f8b66deac183e8eca"
  },
  "ComponentType": "CanvasComponent",
  "CustomGroupControlTemplateName": "",
  "CustomProperties": [
    {
      "Category": 0,
      "DisplayName": "Title",
      "Hidden": false,
      "Name": "Title",
      "PropertyDataTypeKey": "String",
      "Tooltip": "A custom property",
      "Type": "{\"Version\":\"1.341\",\"Type\":{\"Name\":\"Root\",\"Kind\":\"String\",\"EnumString\":\"\",\"Type\":[]}}"
    }
  ],
  "FirstParty": true,
  "Id": "http://microsoft.com/appmagic/Component",
  "IsComponentLocked": false,
  "IsComponentTemplate": true,
  "IsCustomGroupControlTemplate": false,
  "IsPcfControl": false,
  "IsPremiumPcfControl": false,
  "IsWidgetTemplate": false,
  "LastModifiedTimestamp": "638525881219587964",
  "Name": "9a182439b559408f8b66deac183e8eca",
  "OverridableProperties": {},
  "TemplateOriginalName": "04bc41f1995d478cbf5bb0d1916c4750",
  "Version": "1.0"
}